Workbook

Sheet Índice
A1: HouseGreen · Planificación ágil, sprints y pruebas
A4: Sección | B4: Hoja | C4: Contenido
A5: G | B5: G1 Squad | C5: Integrantes, roles Scrum, responsabilidades y capacidad; ceremonias y artefactos
A6: G | B6: G2 Épicas | C6: Épicas con descripción, priorización, historias y puntos
A7: G | B7: G3 Historias de usuario | C7: Historias de usuario en la plantilla: enunciado y criterios de aceptación por escenario
A8: G | B8: G4 Product Backlog | C8: Product Backlog priorizado por valor, urgencia y esfuerzo
A9: G | B9: G5 Estimación | C9: Patrón de comparación para estimar y capacidad del equipo
A10: G | B10: G6 Entregables | C10: Entregables formales con su release y estado
A11: G | B11: G7 Story Map | C11: User Story Map por actividad y release
A12: G | B12: G8 Releases | C12: Release Planning
A13: H | B13: H1 Sprints | C13: Calendario de los 7 sprints (un ciclo por sprint) y horas por integrante
A14: H | B14: H2 Definition of Done | C14: Definition of Done
A15: H | B15: H3 Sprint 1 | C15: Sprint 1 (Documentación fase 1): backlog, avance día a día y burndown
... A32: I | B32: I5 Defectos | C32: Gestión de defectos

Sheet G1 Squad
A1: Squad y responsabilidades
A4: Integrante | B4: Rol Scrum | C4: Responsabilidades | D4: Dedicación (h por semana)
A5: Matías Negrete | B5: Product Owner (documentación) | C5: Define y ordena el Product Backlog según el valor para el inversionista; redacta los criterios de aceptación; acepta o rechaza cada incremento en la Sprint Review (A/R); hace la documentación del proyecto (informe, prototipo, procesos, vistas 4+1 y documentos de dirección) y creó la base de datos junto a José Pizarro. | D5: 10
A6: José Pizarro | B6: Scrum Master (web y backend) | C6: Facilita el Sprint Planning, la Daily, la Review y la Retrospective; mantiene el tablero, el burndown y el registro de impedimentos. Desarrolla la página web, la API, la carga automática de remates (scrapeo) y la conexión de la base de datos con la página; creó la base de datos junto a Matías Negrete. | D6: 10
A7: Basthian Bascuñan | B7: Development Team (aplicación móvil) | C7: Construye y prueba la aplicación móvil del inversionista (front-end terminado el 03-10-2026) y su conexión con la API en Android Studio; estima las historias y propone mejoras técnicas. | D7: 10
A8: Capacidad del equipo por semana (h) | D8: =SUM(D5:D7) -> 30
A10: Responsabilidades por ceremonia y artefacto
A11: Ceremonia o artefacto | B11: Cuándo | C11: Resultado esperado | D11: Responsable | E11: Participan
A12: Sprint Planning | B12: Primer día del sprint · 1 h | C12: Sprint Goal, historias comprometidas y tareas estimadas | D12: José Pizarro | E12: Todo el equipo
A13: Daily Meeting | B13: Cada día · 15 min | C13: Avance, plan del día y bloqueos (pasan al Impediment Log) | D13: José Pizarro | E13: Todo el equipo
A14: Refinamiento del backlog | B14: Una vez por semana · 30 min | C14: Historias con criterios de aceptación y estimación | D14: Matías Negrete | E14: Todo el equipo
A15: Sprint Review | B15: Último día del sprint · 45 min | C15: Incremento aceptado o rechazado (A/R) y backlog ajustado | D15: Matías Negrete | E15: Equipo, docente y usuarios invitados
A16: Retrospective | B16: Último día del sprint · 30 min | C16: Tres mejoras concretas para el sprint siguiente | D16: José Pizarro | E16: Todo el equipo
A17: Product Backlog | B17: Continuo | C17: Orden por valor, urgencia y esfuerzo | D17: Matías Negrete | E17: Todo el equipo
A18: Sprint Backlog, Scrum Board y Burndown | B18: Se actualizan cada día | C18: Avance visible del sprint | D18: José Pizarro | E18: Todo el equipo
A19: Definition of Done | B19: En cada tarea e historia | C19: Calidad pareja del incremento | D19: José Pizarro | E19: Todo el equipo
A20: Incremento (código y pruebas) | B20: Cada sprint | C20: Software que cumple la Definition of Done | D20: José Pizarro y Basthian Bascuñan | E20: Matías Negrete (valida)

Sheet G2 Épicas
A1: Épicas
A4: ID | B4: Épica | C4: Descripción | D4: RF | E4: Entregables | F4: Priorización | G4: Historias | H4: Puntos
A5: E1 | B5: Acceso y seguridad | C5: El usuario se registra, inicia sesión y recupera su acceso; el administrador entra con segundo factor; cada rol ve solo lo que le corresponde y las acciones críticas quedan auditadas. | D5: RF-01, 02, 03 | E5: 4, 5, 17 | F5: 100 | G5: =COUNTIF('G4 Product Backlog'!$C$5:$C$27,A5) -> 4 | H5: =SUMIF('G4 Product Backlog'!$C$5:$C$27,A5,'G4 Product Backlog'!$J$5:$J$27) -> 18
A6: E2 | B6: Propiedades y búsqueda | C6: El inversionista ve el catálogo de remates vigentes, abre la ficha de cada propiedad y filtra por comuna, precio, tipo y zona. | D6: RF-04, 05, 06 | E6: 1, 6 | F6: 100 | G6: =COUNTIF('G4 Product Backlog'!$C$5:$C$27,A6) -> 2 | H6: =SUMIF('G4 Product Backlog'!$C$5:$C$27,A6,'G4 Product Backlog'!$J$5:$J$27) -> 10
A7: E3 | B7: Motor de reglas y semáforo | C7: Cada propiedad recibe su semáforo de forma automática, con la justificación factor por factor, reglas de veto y registro de cada evaluación. | D7: RF-08, 09, 10 | E7: 8, 9, 10 | F7: 100 | G7: =COUNTIF('G4 Product Backlog'!$C$5:$C$27,A7) -> 3 | H7: =SUMIF('G4 Product Backlog'!$C$5:$C$27,A7,'G4 Product Backlog'!$J$5:$J$27) -> 21
A8: E4 | B8: Seguimiento y alertas | C8: El inversionista guarda propiedades, crea filtros y recibe alertas cuando aparece una oportunidad o cambia una que sigue. | D8: RF-07, 11, 12 | E8: 11, 13 | F8: 80 | G8: =COUNTIF('G4 Product Backlog'!$C$5:$C$27,A8) -> 3 | H8: =SUMIF('G4 Product Backlog'!$C$5:$C$27,A8,'G4 Product Backlog'!$J$5:$J$27) -> 14
A9: E5 | B9: Ingesta de datos | C9: Los remates se cargan solos desde rematesinmobiliarios.cl, se validan y se normalizan, sin duplicados. | D9: RF-14 | E9: 14 | F9: 100 | G9: =COUNTIF('G4 Product Backlog'!$C$5:$C$27,A9) -> 1 | H9: =SUMIF('G4 Product Backlog'!$C$5:$C$27,A9,'G4 Product Backlog'!$J$5:$J$27) -> 13
A10: E6 | B10: Geografía y mapa | C10: Las propiedades se ubican por comuna en un mapa, con la cobertura del servicio y el índice de seguridad comunal. | D10: RF-06 | E10: 7, 12 | F10: 80 | G10: =COUNTIF('G4 Product Backlog'!$C$5:$C$27,A10) -> 1 | H10: =SUMIF('G4 Product Backlog'!$C$5:$C$27,A10,'G4 Product Backlog'!$J$5:$J$27) -> 5
A11: E7 | B11: Administración y métricas | C11: El administrador edita fotos y descripción, ve quién vio y guardó cada publicación, envía anuncios y responde opiniones; el analista revisa métricas en modo solo lectura. | D11: RF-14, 15 | E11: 15 | F11: 50 | G11: =COUNTIF('G4 Product Backlog'!$C$5:$C$27,A11) -> 4 | H11: =SUMIF('G4 Product Backlog'!$C$5:$C$27,A11,'G4 Product Backlog'!$J$5:$J$27) -> 21
A12: E8 | B12: App móvil | C12: El inversionista usa HouseGreen en el teléfono: catálogo, detalle, guardados y avisos push. | D12: RF-06, 07, 11 | E12: 2 | F12: 80 | G12: =COUNTIF('G4 Product Backlog'!$C$5:$C$27,A12) -> 1 | H12: =SUMIF('G4 Product Backlog'!$C$5:$C$27,A12,'G4 Product Backlog'!$J$5:$J$27) -> 13
A13: E9 | B13: Plataforma y calidad | C13: API documentada, base de datos, pruebas automatizadas, despliegue de demostración y validación con usuarios. | D13: RF-13, 16 | E13: 3, 16, 18, 19 | F13: 100 | G13: =COUNTIF('G4 Product Backlog'!$C$5:$C$27,A13) -> 4 | H13: =SUMIF('G4 Product Backlog'!$C$5:$C$27,A13,'G4 Product Backlog'!$J$5:$J$27) -> 21
A14: Total | G14: =SUM(G5:G13) -> 23 | H14: =SUM(H5:H13) -> 136
B16: Escala de priorización
B17: Priorización | C17: Significado
B18: 100 | C18: Imprescindible para el MVP (Release 1)
B19: 80 | C19: Necesaria para la propuesta completa
B20: 50 | C20: Complementa la operación

Sheet G3 Historias de usuario
A1: Historias de usuario
A4: Enunciado de la historia | E4: Criterios de aceptación
A5: ID de la historia | B5: Rol | C5: Funcionalidad | D5: Resultado | E5: N.º de escenario | F5: Criterio de aceptación (título) | G5: Contexto | H5: Evento | I5: Comportamiento esperado
A6: HU-01 (E1 · 5 pts) | B6: Inversionista | C6: Registrarme e iniciar sesión con correo y contraseña | D6: Acceder de forma segura a la plataforma | E6: 1 | F6: Registro válido | G6: El correo no está registrado | H6: Cuando envío el formulario con un correo válido y una contraseña de 8 o más caracteres | I6: Se crea la cuenta con rol inversionista y la contraseña se guarda cifrada con bcrypt
E7: 2 | F7: Correo ya registrado | G7: Existe una cuenta con ese correo | H7: Cuando intento registrarme | I7: El sistema rechaza el registro con un mensaje claro y no crea otra cuenta
E8: 3 | F8: Contraseña incorrecta | G8: Tengo una cuenta creada | H8: Cuando inicio sesión con una contraseña errónea | I8: Responde 401 con un mensaje genérico, sin revelar si el correo existe
A9: HU-02 (E2 · 5 pts) | B9: Inversionista | C9: Ver el catálogo de remates vigentes | D9: Conocer las oportunidades disponibles | E9: 1 | F9: Remates vigentes | G9: Hay propiedades activas | H9: Cuando abro el catálogo | I9: Veo cada propiedad con comuna, tipo, precio mínimo, fecha del remate, zona y puntaje del semáforo
E10: 2 | F10: Sin remates | G10: No hay propiedades activas | H10: Cuando abro el catálogo | I10: Veo el mensaje «No hay remates vigentes», sin errores
E11: 3 | F11: Remate terminado | G11: La propiedad ya fue rematada o su fecha pasó | H11: Cuando abro el catálogo | I11: La propiedad no aparece entre las vigentes
A12: HU-03 (E3 · 8 pts) | B12: Inversionista | C12: Que cada propiedad tenga su semáforo calculado automáticamente | D12: Saber de inmediato su nivel de riesgo | E12: 1 | F12: Propiedad completa | G12: La propiedad tiene los datos de los 4 factores | H12: Cuando se guarda o se actualiza | I12: Se calcula el puntaje de 0 a 8 y la zona (6 a 8 verde, 3 a 5 amarilla, 0 a 2 roja) y se guarda la evaluación. Reglas del 05-10-2026 (4 factores): falta aplicarlas en la base de datos
E13: 2 | F13: Dato faltante | G13: Falta un factor, por ejemplo los comparables | H13: Cuando se evalúa | I13: Ese factor se evalúa con 0 puntos y se muestra «Por verificar», porque sin el dato no se puede sacar una conclusión
E14: 3 | F14: Veto | G14: Tiene usufructo vitalicio, herencia no resuelta, prohibición de expropiación o descuento real menor a 15 % | H14: Cuando se evalúa | I14: Queda en zona roja por veto y se guarda el motivo
A15: HU-04 (E9 · 3 pts) | B15: Equipo de desarrollo | C15: Una API REST documentada en /api/v1 | D15: Que la web, la app y el panel usen la misma lógica | E15: 1 | F15: Documentación | G15: La API está en ejecución | H15: Cuando abro /docs | I15: Todos los endpoints de /api/v1 aparecen documentados (OpenAPI) con sus esquemas
E16: 2 | F16: Datos inválidos | G16: Envío un cuerpo con datos inválidos | H16: Cuando llamo a un endpoint | I16: Responde 422 con {código, mensaje}, sin detalles internos
E17: 3 | F17: Sin token | G17: El endpoint está protegido | H17: Cuando lo llamo sin token o con uno vencido | I17: Responde 401
A18: HU-05 (E3 · 5 pts) | B18: Inversionista | C18: Ver en el detalle la justificación del semáforo factor por factor | D18: Confiar en la clasificación | E18: 1 | F18: Detalle con justificación | G18: La propiedad tiene una evaluación | H18: Cuando abro el detalle | I18: Veo los 4 factores con su valor, zona, puntos y fuente, y el puntaje total
E19: 2 | F19: Propiedad vetada | G19: La evaluación tiene un veto | H19: Cuando abro el detalle | I19: Veo «Zona roja por veto» y el motivo
E20: 3 | F20: Historial | G20: La propiedad tuvo evaluaciones anteriores | H20: Cuando abro el historial | I20: Veo la fecha, el puntaje y la zona de cada evaluación
A21: HU-06 (E2 · 5 pts) | B21: Inversionista | C21: Filtrar por comuna, precio, tipo y zona | D21: Encontrar lo que calza con mi estrategia | E21: 1 | F21: Filtro combinado | G21: Hay propiedades de varias comunas y precios | H21: Cuando filtro por Maipú y precio hasta $80.000.000 | I21: Solo aparecen las que cumplen ambos filtros, en 2 segundos o menos
E22: 2 | F22: Filtro por zona | G22: Hay propiedades en las tres zonas | H22: Cuando filtro por zona verde | I22: Solo aparecen propiedades en zona verde
E23: 3 | F23: Sin coincidencias | G23: Ninguna propiedad cumple los filtros | H23: Cuando aplico los filtros | I23: Veo «Sin resultados» y la opción para limpiar los filtros
A24: HU-07 (E4 · 3 pts) | B24: Inversionista | C24: Guardar propiedades | D24: Seguirlas hasta el día del remate | E24: 1 | F24: Guardar | G24: Estoy en el catálogo o en el detalle | H24: Cuando toco «Guardar» | I24: La propiedad aparece en Guardados y se mantiene al cerrar y volver a abrir la sesión
E25: 2 | F25: Quitar | G25: Tengo una propiedad guardada | H25: Cuando la quito y confirmo | I25: Desaparece de mi lista
E26: 3 | F26: Datos ajenos | G26: Otro usuario tiene propiedades guardadas | H26: Cuando pido sus guardados cambiando el id | I26: Responde 403 o 404, sin mostrar datos ajenos
A27: HU-08 (E7 · 3 pts) | B27: Administrador | C27: Editar las fotos y la descripción de una publicación | D27: Mejorar su presentación sin alterar los datos del remate | E27: 1 | F27: Editar descripción | G27: Estoy en una publicación | H27: Cuando guardo una descripción de hasta 1.000 caracteres | I27: La ficha muestra la nueva descripción y el cambio queda auditado
E28: 2 | F28: Fotos | G28: Estoy en una publicación | H28: Cuando subo, ordeno o elijo la portada (hasta 15 fotos) | I28: La ficha muestra las fotos en ese orden, con la portada elegida
E29: 3 | F29: Datos del remate | G29: Estoy en una publicación | H29: Cuando intento cambiar el precio, la fecha o el tribunal | I29: No es posible: esos campos no se editan y la API responde 403
A30: HU-09 (E1 · 5 pts) | B30: Administrador | C30: Iniciar sesión con un segundo factor | D30: Proteger el panel de administración | E30: 1 | F30: Código válido | G30: Tengo el segundo factor activo | H30: Cuando ingreso correo, contraseña y un código TOTP vigente | I30: Entro al panel
E31: 2 | F31: Código vencido o usado | G31: Tengo el segundo factor activo | H31: Cuando ingreso un código vencido o ya usado | I31: Se niega el acceso y el intento queda en la auditoría
E32: 3 | F32: Intentos fallidos | G32: Fallé 5 veces seguidas | H32: Cuando intento entrar de nuevo | I32: La cuenta queda bloqueada 15 minutos
A33: HU-10 (E5 · 13 pts) | B33: Administrador | C33: Que los remates se carguen solos desde https://www.rematesinmobiliarios.cl/ cada 6 horas | D33: Que el catálogo esté al día | E33: 1 | F33: Carga programada | G33: El planificador está activo | H33: Cuando se cumplen 6 horas desde la última carga | I33: Se leen los remates publicados, se cargan los nuevos y se registra la ejecución con cargados y errores
E34: 2 | F34: Aviso incompleto | G34: Un aviso viene sin rol de avalúo | H34: Cuando se procesa | I34: Se descarta, queda registrado el error y la carga continúa
E35: 3 | F35: Aviso repetido | G35: El aviso ya fue cargado | H35: Cuando se lee otra vez | I35: No se duplica la propiedad; se actualiza si cambió
A36: HU-11 (E3 · 8 pts) | B36: Administrador | C36: Configurar umbrales, vetos e índice comunal | D36: Ajustar el semáforo sin tocar el código | E36: 1 | F36: Cambiar un umbral | G36: Estoy en Reglas del semáforo | H36: Cuando cambio el umbral verde del factor 1 y guardo | I36: Se crea una nueva versión de reglas y se recalculan las publicaciones activas
E37: 2 | F37: Umbral inválido | G37: Estoy editando un factor | H37: Cuando dejo el umbral verde por debajo del rojo | I37: No se guarda y el sistema explica el error
E38: 3 | F38: Índice comunal | G38: Estoy en Seguridad por comuna | H38: Cuando cambio el nivel de una comuna | I38: Queda con su fecha de vigencia y se recalculan sus propiedades
A39: HU-12 (E1 · 3 pts) | B39: Inversionista | C39: Recuperar mi contraseña por correo | D39: No perder el acceso a mi cuenta | E39: 1 | F39: Solicitud | G39: Olvidé mi contraseña | H39: Cuando ingreso mi correo | I39: Veo el mismo mensaje exista o no la cuenta; si existe, llega un enlace de un solo uso que vence en 30 minutos
E40: 2 | F40: Enlace vencido o usado | G40: Recibí un enlace | H40: Cuando lo abro después de 30 minutos o por segunda vez | I40: Se rechaza y puedo pedir uno nuevo
A41: HU-13 (E4 · 8 pts) | B41: Inversionista | C41: Recibir alertas cuando aparezca una propiedad que calce con mis filtros | D41: No perder oportunidades | E41: 1 | F41: Nueva coincidencia | G41: Tengo un filtro guardado y activo | H41: Cuando la ingesta carga una propiedad que calza | I41: Recibo una alerta (app, push o correo) en menos de 5 minutos
E42: 2 | F42: Filtro inactivo | G42: Desactivé mi filtro | H42: Cuando llega una propiedad que calza | I42: No recibo alerta
E43: 3 | F43: Cambio de zona | G43: Guardé una propiedad | H43: Cuando cambia su zona del semáforo | I43: Recibo el aviso «Pasó a zona …»
A44: HU-14 (E4 · 3 pts) | B44: Inversionista | C44: Ver el historial de alertas | D44: Revisar cambios de precio y de zona | E44: 1 | F44: Ver historial | G44: Recibí alertas | H44: Cuando abro Notificaciones | I44: Veo cada alerta con fecha, tipo y propiedad, de la más nueva a la más antigua
E45: 2 | F45: Marcar como leída | G45: Tengo alertas sin leer | H45: Cuando abro una | I45: Queda leída y baja el contador
A46: HU-15 (E6 · 5 pts) | B46: Inversionista | C46: Ver los remates en un mapa por comuna | D46: Ubicar las oportunidades | E46: 1 | F46: Mapa por comuna | G46: Hay propiedades en varias comunas | H46: Cuando abro el mapa | I46: Veo las propiedades por comuna con su zona y una leyenda con texto e ícono, no solo color
E47: 2 | F47: Sin coordenadas | G47: Una propiedad no tiene coordenadas | H47: Cuando abro el mapa | I47: Aparece en el centro de su comuna con la marca «ubicación aproximada»
E48: 3 | F48: Fuera de cobertura | G48: Consulto una comuna fuera de la cobertura | H48: Cuando la selecciono | I48: Veo que está fuera de la zona de cobertura
A49: HU-16 (E8 · 13 pts) | B49: Inversionista | C49: Usar HouseGreen en el teléfono y recibir avisos push | D49: Revisar oportunidades en terreno | E49: 1 | F49: Instalar y entrar | G49: Tengo un teléfono Android o iOS | H49: Cuando instalo la app e inicio sesión | I49: La app funciona sin cierres inesperados
E50: 2 | F50: Aviso push | G50: Tengo alertas activas | H50: Cuando llega una alerta | I50: Recibo un aviso push que abre el detalle de la propiedad
E51: 3 | F51: Guardados sincronizados | G51: Guardé propiedades en la web | H51: Cuando abro la app | I51: Veo las mismas propiedades guardadas
A52: HU-17 (E7 · 8 pts) | B52: Analista | C52: Ver métricas de subastas, usuarios y alcance en modo solo lectura | D52: Evaluar la tracción del producto | E52: 1 | F52: Ver métricas | G52: Entro como analista | H52: Cuando abro Resumen, Subastas, Usuarios o Alcance | I52: Veo los gráficos y puedo cambiar el período (7 días, 30 días o 12 meses)
E53: 2 | F53: Intento de escritura | G53: Entro como analista | H53: Cuando intento crear, editar o enviar algo | I53: La API responde 403 y la interfaz no muestra acciones de edición
A54: HU-18 (E7 · 5 pts) | B54: Administrador | C54: Enviar anuncios y responder opiniones autorizadas | D54: Comunicarme con los usuarios | E54: 1 | F54: Anuncio a un grupo | G54: Una publicación tiene personas que la guardaron | H54: Cuando envío un anuncio a ese grupo | I54: Solo ellos lo reciben y queda registrado quién lo leyó
E55: 2 | F55: Opinión autorizada | G55: El usuario autorizó una respuesta | H55: Cuando respondo | I55: La respuesta le llega por correo y en sus notificaciones
E56: 3 | F56: Opinión sin autorización | G56: El usuario no autorizó respuesta | H56: Cuando abro su opinión | I56: No aparece la opción de responder
A57: HU-19 (E9 · 8 pts) | B57: Responsable de calidad | C57: Pruebas automatizadas que corran en cada cambio | D57: Detectar errores antes de entregar | E57: 1 | F57: Cada cambio | G57: Se abre un pull request | H57: Cuando se sube el cambio | I57: GitHub Actions ejecuta las pruebas; si una falla, el cambio no se integra
E58: 2 | F58: Bordes de las reglas | G58: Existen las pruebas del motor | H58: Cuando corren | I58: Cubren los bordes de cada umbral, por ejemplo 14,9 %, 15 %, 39,9 % y 40 % de descuento
A59: HU-20 (E9 · 5 pts) | B59: Equipo de desarrollo | C59: Desplegar la web, la API, el worker y la base en la nube | D59: Demostrar la solución funcionando | E59: 1 | F59: Demostración en la nube | G59: El código está en la rama principal | H59: Cuando se despliega en Railway | I59: Web, API, worker y base funcionan con HTTPS y /health responde 200
E60: 2 | F60: Secretos | G60: Hay claves y contraseñas de servicios | H60: Cuando se revisa el repositorio | I60: Ninguna clave está en el código; todas están en variables de entorno
A61: HU-21 (E9 · 5 pts) | B61: Product Owner | C61: Validar el producto con inversionistas | D61: Confirmar que resuelve el problema | E61: 1 | F61: Prueba con 5 inversionistas | G61: El producto está desplegado | H61: Cuando cada participante se registra y busca propiedades | I61: Lo logra en menos de 5 minutos y el SUS promedio supera 68
E62: 2 | F62: Hallazgos | G62: Terminó la prueba | H62: Cuando se analizan los resultados | I62: Cada problema queda como defecto o historia en el backlog
A63: HU-22 (E1 · 5 pts) | B63: Administrador | C63: Que las acciones críticas queden auditadas y que la API tenga límites de uso | D63: Proteger la plataforma | E63: 1 | F63: Acción crítica | G63: Soy administrador | H63: Cuando edito una publicación | I63: Queda registrado quién, qué y cuándo
E64: 2 | F64: Límite de uso | G64: Una misma IP intenta iniciar sesión | H64: Cuando supera 5 intentos por minuto | I64: La API responde 429
E65: 3 | F65: Rol sin permiso | G65: Soy inversionista | H65: Cuando intento crear o editar una propiedad | I65: La API responde 403
A66: HU-23 (E7 · 5 pts) | B66: Administrador | C66: Ver cuántas personas vieron y guardaron cada publicación | D66: Enviar anuncios a los interesados | E66: 1 | F66: Lista de publicaciones | G66: Hay publicaciones con vistas y guardados | H66: Cuando abro Publicaciones | I66: Veo cada una con zona, comuna, vistas y guardados, y puedo ordenar por más vistas, más guardadas, comuna o zona
E67: 2 | F67: Conteo de vistas | G67: Un inversionista abre el detalle varias veces en 30 minutos | H67: Cuando se registran las vistas | I67: Cuenta una sola visita; las de administradores y analistas no cuentan
E68: 3 | F68: Quién la vio y la guardó | G68: Estoy en una publicación | H68: Cuando abro sus pestañas | I68: Veo «La vieron» y «La guardaron» con nombre y fecha

Sheet G4 Product Backlog
A1: Product Backlog priorizado
A4: Orden | B4: ID | C4: Épica | D4: Historia de usuario | E4: RF o entregable | F4: Valor (1 a 5) | G4: Urgencia (1 a 5) | H4: Puntaje (V × U) | I4: Prioridad | J4: Puntos | K4: Sprint (plan 24-09) | L4: Sprint (al 04-10) | M4: Release | N4: Estado
A5: 1 | B5: HU-01 | C5: E1 | D5: Como inversionista, quiero registrarme e iniciar sesión con correo y contraseña, para acceder de forma segura a la plataforma. | E5: RF-01 | F5: 5 | G5: 5 | H5: =F5*G5 -> 25 | I5: =IF(H5>=16,"Alta",IF(H5>=9,"Media","Baja")) -> Alta | J5: 5 | K5: 3 | L5: 4 | M5: =IF(L5<=5,"R1",IF(L5<=7,"R2","R3")) -> R1 | N5: Hecho
A6: 2 | B6: HU-02 | C6: E2 | D6: Como inversionista, quiero ver el catálogo de remates vigentes, para conocer las oportunidades disponibles. | E6: RF-04 | F6: 5 | G6: 5 | H6: =F6*G6 -> 25 | I6: =IF(H6>=16,"Alta",IF(H6>=9,"Media","Baja")) -> Alta | J6: 5 | K6: 3 | L6: 5 | M6: =IF(L6<=5,"R1",IF(L6<=7,"R2","R3")) -> R1 | N6: Hecho
A7: 3 | B7: HU-03 | C7: E3 | D7: Como inversionista, quiero que cada propiedad tenga su semáforo calculado automáticamente, para saber de inmediato su nivel de riesgo. | E7: RF-08 | F7: 5 | G7: 5 | H7: =F7*G7 -> 25 | I7: =IF(H7>=16,"Alta",IF(H7>=9,"Media","Baja")) -> Alta | J7: 8 | K7: 3 | L7: 4 | M7: =IF(L7<=5,"R1",IF(L7<=7,"R2","R3")) -> R1 | N7: Hecho
A8: 4 | B8: HU-07 | C8: E4 | D8: Como inversionista, quiero guardar propiedades, para seguirlas hasta el día del remate. | E8: RF-07 | F8: 4 | G8: 3 | H8: =F8*G8 -> 12 | I8: =IF(H8>=16,"Alta",IF(H8>=9,"Media","Baja")) -> Media | J8: 3 | K8: 4 | L8: 5 | M8: =IF(L8<=5,"R1",IF(L8<=7,"R2","R3")) -> R1 | N8: Hecho
A9: 5 | B9: HU-04 | C9: E9 | D9: Como equipo de desarrollo, quiero una API REST documentada en /api/v1, para que la web, la app y el panel usen la misma lógica. | E9: RF-13 | F9: 4 | G9: 5 | H9: =F9*G9 -> 20 | I9: =IF(H9>=16,"Alta",IF(H9>=9,"Media","Baja")) -> Alta | J9: 3 | K9: 4 | L9: 6 | M9: =IF(L9<=5,"R1",IF(L9<=7,"R2","R3")) -> R2 | N9: Por hacer
A10: 6 | B10: HU-05 | C10: E3 | D10: Como inversionista, quiero ver en el detalle la justificación del semáforo factor por factor, para confiar en la clasificación. | E10: RF-09 | F10: 5 | G10: 4 | H10: =F10*G10 -> 20 | I10: =IF(H10>=16,"Alta",IF(H10>=9,"Media","Baja")) -> Alta | J10: 5 | K10: 4 | L10: 4 | M10: =IF(L10<=5,"R1",IF(L10<=7,"R2","R3")) -> R1 | N10: Hecho
A11: 7 | B11: HU-06 | C11: E2 | D11: Como inversionista, quiero filtrar por comuna, precio, tipo y zona, para encontrar lo que calza con mi estrategia. | E11: RF-06 | F11: 4 | G11: 4 | H11: =F11*G11 -> 16 | I11: =IF(H11>=16,"Alta",IF(H11>=9,"Media","Baja")) -> Alta | J11: 5 | K11: 4 | L11: 5 | M11: =IF(L11<=5,"R1",IF(L11<=7,"R2","R3")) -> R1 | N11: Hecho
A12: 8 | B12: HU-08 | C12: E7 | D12: Como administrador, quiero editar las fotos y la descripción de una publicación, para mejorar su presentación sin alterar los datos del remate. | E12: RF-14 | F12: 3 | G12: 4 | H12: =F12*G12 -> 12 | I12: =IF(H12>=16,"Alta",IF(H12>=9,"Media","Baja")) -> Media | J12: 3 | K12: 4 | L12: 4 | M12: =IF(L12<=5,"R1",IF(L12<=7,"R2","R3")) -> R1 | N12: Hecho
A13: 9 | B13: HU-23 | C13: E7 | D13: Como administrador, quiero ver cuántas personas vieron y guardaron cada publicación, para enviar anuncios a los interesados. | E13: RF-15 | F13: 3 | G13: 3 | H13: =F13*G13 -> 9 | I13: =IF(H13>=16,"Alta",IF(H13>=9,"Media","Baja")) -> Media | J13: 5 | K13: Nueva | L13: 4 | M13: =IF(L13<=5,"R1",IF(L13<=7,"R2","R3")) -> R1 | N13: Hecho
A14: 10 | B14: HU-10 | C14: E5 | D14: Como administrador, quiero que los remates se carguen solos desde https://www.rematesinmobiliarios.cl/ cada 6 horas, para que el catálogo esté al día. | E14: RF-14 | F14: 5 | G14: 4 | H14: =F14*G14 -> 20 | I14: =IF(H14>=16,"Alta",IF(H14>=9,"Media","Baja")) -> Alta | J14: 13 | K14: 5 | L14: 4 | M14: =IF(L14<=5,"R1",IF(L14<=7,"R2","R3")) -> R1 | N14: Hecho
A15: 11 | B15: HU-09 | C15: E1 | D15: Como administrador, quiero iniciar sesión con un segundo factor, para proteger el panel de administración. | E15: RF-02 | F15: 4 | G15: 4 | H15: =F15*G15 -> 16 | I15: =IF(H15>=16,"Alta",IF(H15>=9,"Media","Baja")) -> Alta | J15: 5 | K15: 5 | L15: — | M15: =IF(L15<=5,"R1",IF(L15<=7,"R2","R3")) -> R3 | N15: Por hacer
A16: 12 | B16: HU-12 | C16: E1 | D16: Como inversionista, quiero recuperar mi contraseña por correo, para no perder el acceso a mi cuenta. | E16: RF-03 | F16: 3 | G16: 3 | H16: =F16*G16 -> 9 | I16: =IF(H16>=16,"Alta",IF(H16>=9,"Media","Baja")) -> Media | J16: 3 | K16: 5 | L16: 5 | M16: =IF(L16<=5,"R1",IF(L16<=7,"R2","R3")) -> R1 | N16: En curso
A17: 13 | B17: HU-11 | C17: E3 | D17: Como administrador, quiero configurar umbrales, vetos e índice comunal, para ajustar el semáforo sin tocar el código. | E17: RF-10 | F17: 4 | G17: 3 | H17: =F17*G17 -> 12 | I17: =IF(H17>=16,"Alta",IF(H17>=9,"Media","Baja")) -> Media | J17: 8 | K17: 6 | L17: — | M17: =IF(L17<=5,"R1",IF(L17<=7,"R2","R3")) -> R3 | N17: Descartada
A18: 14 | B18: HU-13 | C18: E4 | D18: Como inversionista, quiero recibir alertas cuando aparezca una propiedad que calce con mis filtros, para no perder oportunidades. | E18: RF-11 | F18: 4 | G18: 3 | H18: =F18*G18 -> 12 | I18: =IF(H18>=16,"Alta",IF(H18>=9,"Media","Baja")) -> Media | J18: 8 | K18: 6 | L18: 6 | M18: =IF(L18<=5,"R1",IF(L18<=7,"R2","R3")) -> R2 | N18: Por hacer
A19: 15 | B19: HU-15 | C19: E6 | D19: Como inversionista, quiero ver los remates en un mapa por comuna, para ubicar las oportunidades. | E19: Entreg. 7 y 12 | F19: 3 | G19: 3 | H19: =F19*G19 -> 9 | I19: =IF(H19>=16,"Alta",IF(H19>=9,"Media","Baja")) -> Media | J19: 5 | K19: 6 | L19: 5 | M19: =IF(L19<=5,"R1",IF(L19<=7,"R2","R3")) -> R1 | N19: En curso
A20: 16 | B20: HU-14 | C20: E4 | D20: Como inversionista, quiero ver el historial de alertas, para revisar cambios de precio y de zona. | E20: RF-12 | F20: 2 | G20: 3 | H20: =F20*G20 -> 6 | I20: =IF(H20>=16,"Alta",IF(H20>=9,"Media","Baja")) -> Baja | J20: 3 | K20: 6 | L20: 6 | M20: =IF(L20<=5,"R1",IF(L20<=7,"R2","R3")) -> R2 | N20: Por hacer
A21: 17 | B21: HU-19 | C21: E9 | D21: Como responsable de calidad, quiero pruebas automatizadas que corran en cada cambio, para detectar errores antes de entregar. | E21: RF-16 | F21: 4 | G21: 4 | H21: =F21*G21 -> 16 | I21: =IF(H21>=16,"Alta",IF(H21>=9,"Media","Baja")) -> Alta | J21: 8 | K21: 7 | L21: 6 | M21: =IF(L21<=5,"R1",IF(L21<=7,"R2","R3")) -> R2 | N21: Por hacer
A22: 18 | B22: HU-22 | C22: E1 | D22: Como administrador, quiero que las acciones críticas queden auditadas y que la API tenga límites de uso, para proteger la plataforma. | E22: Entreg. 17 | F22: 4 | G22: 4 | H22: =F22*G22 -> 16 | I22: =IF(H22>=16,"Alta",IF(H22>=9,"Media","Baja")) -> Alta | J22: 5 | K22: 7 | L22: — | M22: =IF(L22<=5,"R1",IF(L22<=7,"R2","R3")) -> R3 | N22: Por hacer
A23: 19 | B23: HU-17 | C23: E7 | D23: Como analista, quiero ver métricas de subastas, usuarios y alcance en modo solo lectura, para evaluar la tracción del producto. | E23: RF-15 | F23: 2 | G23: 4 | H23: =F23*G23 -> 8 | I23: =IF(H23>=16,"Alta",IF(H23>=9,"Media","Baja")) -> Baja | J23: 8 | K23: 7 | L23: 5 | M23: =IF(L23<=5,"R1",IF(L23<=7,"R2","R3")) -> R1 | N23: En curso
A24: 20 | B24: HU-18 | C24: E7 | D24: Como administrador, quiero enviar anuncios y responder opiniones autorizadas, para comunicarme con los usuarios. | E24: Entreg. 15 | F24: 2 | G24: 3 | H24: =F24*G24 -> 6 | I24: =IF(H24>=16,"Alta",IF(H24>=9,"Media","Baja")) -> Baja | J24: 5 | K24: 7 | L24: 5 | M24: =IF(L24<=5,"R1",IF(L24<=7,"R2","R3")) -> R1 | N24: En curso
A25: 21 | B25: HU-20 | C25: E9 | D25: Como equipo de desarrollo, quiero desplegar la web, la API, el worker y la base en la nube, para demostrar la solución funcionando. | E25: Entreg. 19 | F25: 4 | G25: 4 | H25: =F25*G25 -> 16 | I25: =IF(H25>=16,"Alta",IF(H25>=9,"Media","Baja")) -> Alta | J25: 5 | K25: 8 | L25: 6 | M25: =IF(L25<=5,"R1",IF(L25<=7,"R2","R3")) -> R2 | N25: Por hacer
A26: 22 | B26: HU-16 | C26: E8 | D26: Como inversionista, quiero usar HouseGreen en el teléfono y recibir avisos push, para revisar oportunidades en terreno. | E26: Entreg. 2 | F26: 4 | G26: 3 | H26: =F26*G26 -> 12 | I26: =IF(H26>=16,"Alta",IF(H26>=9,"Media","Baja")) -> Media | J26: 13 | K26: 8 | L26: 6 | M26: =IF(L26<=5,"R1",IF(L26<=7,"R2","R3")) -> R2 | N26: En curso
A27: 23 | B27: HU-21 | C27: E9 | D27: Como Product Owner, quiero validar el producto con inversionistas, para confirmar que resuelve el problema. | E27: Objetivo 7 | F27: 5 | G27: 4 | H27: =F27*G27 -> 20 | I27: =IF(H27>=16,"Alta",IF(H27>=9,"Media","Baja")) -> Alta | J27: 5 | K27: 9 | L27: 7 | M27: =IF(L27<=5,"R1",IF(L27<=7,"R2","R3")) -> R2 | N27: Por hacer
A28: Total | J28: =SUM(J5:J27) -> 136
A30: Puntos por sprint
A31: Sprint | B31: Puntos | C31: Release
A32: 1 | B32: =SUMIF($L$5:$L$27,A32,$J$5:$J$27) -> 0 | C32: —
A33: 2 | B33: =SUMIF($L$5:$L$27,A33,$J$5:$J$27) -> 0 | C33: —
A34: 3 | B34: =SUMIF($L$5:$L$27,A34,$J$5:$J$27) -> 0 | C34: —
A35: 4 | B35: =SUMIF($L$5:$L$27,A35,$J$5:$J$27) -> 39 | C35: R1
A36: 5 | B36: =SUMIF($L$5:$L$27,A36,$J$5:$J$27) -> 34 | C36: R1
A37: 6 | B37: =SUMIF($L$5:$L$27,A37,$J$5:$J$27) -> 40 | C37: R2
A38: 7 | B38: =SUMIF($L$5:$L$27,A38,$J$5:$J$27) -> 5 | C38: R2

Sheet G5 Estimación
A1: Estimación: patrón de comparación
A4: Puntos | B4: Complejidad | C4: Esfuerzo | D4: Incertidumbre y dependencias | E4: Historia de referencia
A5: 3 | B5: Baja | C5: Una tarde o menos por integrante | D5: Sin dependencias ni dudas técnicas | E5: HU-07 · Guardar propiedades
A6: 5 | B6: Media | C6: Un endpoint, su pantalla y sus pruebas | D6: Pocas dependencias | E6: HU-01 · Registro e inicio de sesión
A7: 8 | B7: Alta | C7: Varias reglas de negocio y casos borde | D7: Depende de datos de varias tablas | E7: HU-03 · Semáforo automático
A8: 13 | B8: Muy alta | C8: Integración con un sistema externo | D8: Alta incertidumbre: la fuente puede cambiar o fallar | E8: HU-10 · Carga automática de remates
C10: Capacidad y velocidad
C11: Parámetro | D11: Valor
C12: Integrantes del equipo | D12: =COUNTA('G1 Squad'!A5:A7) -> 3
C13: Horas por semana de cada integrante | D13: 10
C14: Semanas del proyecto | D14: 11
C15: Horas disponibles del proyecto | D15: =D12*D13*D14 -> 330
C16: Puntos del plan de entrega (sprints 4 a 7) | D16: =SUM('H1 Sprints'!F5:F11) -> 118
C17: Horas disponibles por punto | D17: =ROUND(D15/D16,1) -> 2.8
C18: Técnica de estimación | D18: Planning Poker con la serie de Fibonacci (1, 2, 3, 5, 8, 13)

Sheet G6 Entregables
A1: Definición de entregables
A4: N.º | B4: Entregable | C4: Épica | D4: Historias | E4: Release | F4: Estado al 04-10 | G4: Evidencia
A5: 1 | B5: Plataforma web HouseGreen | C5: E2 | D5: HU-02, 05, 06 | E5: R1 | F5: Implementado | G5: React 19 + Vite: catálogo desde la API, sesión con /auth/me, detalle y guardados por API (29-09)
A6: 2 | B6: Aplicación móvil para inversionistas | C6: E8 | D6: HU-16 | E6: R2 | F6: Implementado | G6: Front-end terminado el 03-10-2026; la conexión con la API se hace en el Sprint 6 (Android Studio)
A7: 3 | B7: Backend API REST | C7: E9 | D7: HU-04 | E7: R2 | F7: En desarrollo | G7: FastAPI: autenticación, propiedades, vistas, favoritos, alertas y comunas
A8: 4 | B8: Módulo de autenticación y 2FA | C8: E1 | D8: HU-01, 09, 12 | E8: R1 | F8: Implementado | G8: Registro e inicio de sesión con JWT y bcrypt; /auth/me (29-09). La verificación en dos pasos (HU-09) está en el backlog, sin sprint
A9: 5 | B9: Gestión de usuarios y roles | C9: E1 | D9: HU-17, 22 | E9: R1 | F9: Implementado | G9: Roles 1, 2 y 3; rutas y menú del administrador solo para su rol (29-09)
A10: 6 | B10: Módulo de propiedades | C10: E2 | D10: HU-02, 06 | E10: R1 | F10: En desarrollo | G10: CRUD en la API; DEF-01 y DEF-03 corregidos (01-10 y 04-10), falta la re-prueba
A11: 7 | B11: Módulo de geografía | C11: E6 | D11: HU-15 | E11: R1 | F11: Implementado | G11: Tabla de comunas y endpoint /comunas
A12: 8 | B12: Motor de reglas y semáforo | C12: E3 | D12: HU-03 | E12: R1 | F12: Implementado | G12: calculate_score() en PL/pgSQL; umbrales corregidos (28-09); reglas probadas (30-09)
A13: 9 | B13: Administrador del motor de reglas | C13: E3 | D13: HU-11 | E13: R3 | F13: Descartada | G13: Pantallas diseñadas; historia descartada el 29-09: el administrador no configura las reglas
A14: 10 | B14: Trazabilidad de evaluaciones | C14: E3 | D14: HU-05 | E14: R1 | F14: Implementado | G14: property_evaluations y evaluation_details
A15: 11 | B15: Módulo de propiedades guardadas | C15: E4 | D15: HU-07 | E15: R1 | F15: Implementado | G15: La web usa GET, POST y DELETE /favoritos (29-09)
A16: 12 | B16: Módulo de cobertura | C16: E6 | D16: HU-15 | E16: R1 | F16: Diseñado | G16: coverage_zones en el modelo de datos
... A23: 19 | B23: Despliegue de la solución | C23: E9 | D23: HU-20 | E23: R2 | F23: Planificado | G23: Arquitectura de despliegue en Railway

Sheet G7 Story Map
A1: User Story Mapping
A4: Release | B4: Acceder | C4: Buscar remates | D4: Evaluar una propiedad | E4: Hacer seguimiento | F4: Administrar datos | G4: Operar y analizar
A5: R1 · MVP web Sprints 4 y 5 al 13-10-2026 | B5: HU-01 Registrarse e iniciar sesión | C5: HU-02 Ver el catálogo | D5: HU-03 Semáforo automático | E5: HU-07 Guardar propiedades | F5: HU-08 Fotos y descripción | G5: HU-17 Panel del analista
B6: HU-12 Recuperar contraseña | C6: HU-06 Filtros | D6: HU-05 Justificación por factor | F6: HU-10 Carga automática de remates | G6: HU-18 Anuncios y opiniones
C7: HU-15 Mapa por comuna | F7: HU-23 Vistas y guardados por publicación
A8: R2 · Conexión, pruebas y cierre Sprints 6 a 7 al 04-11-2026 | C8: HU-16 App móvil | E8: HU-13 Alertas por filtros | G8: HU-04 API documentada /api/v1
E9: HU-14 Historial de alertas | G9: HU-19 Pruebas automatizadas
G10: HU-20 Despliegue de demostración
G11: HU-21 Validación con usuarios
A12: R3 · Backlog sin sprint asignado | B12: HU-09 2FA del administrador | D12: HU-11 Reglas e índice comunal (descartada)
B13: HU-22 Seguridad y auditoría
A14: Verde: historia hecha. Crema: en curso. Blanco: por hacer.

Sheet G8 Releases
A1: Release Planning
A4: Release | B4: Nombre | C4: Sprints | D4: Término | E4: Qué puede hacer el usuario al final | F4: Historias | G4: Puntos | H4: Entregables (N.º)
A5: R1 | B5: MVP web | C5: 4 y 5 | D5: 46308 | E5: Registrarse, ver el catálogo con remates reales de rematesinmobiliarios.cl, filtrar, abrir el detalle con el semáforo explicado, guardar propiedades y recibir anuncios; el administrador edita fotos y descripción y ve quién vio cada publicación; el analista ve las métricas. | F5: HU-01, HU-02, HU-03, HU-05, HU-06, HU-07, HU-08, HU-10, HU-12, HU-15, HU-17, HU-18, HU-23 | G5: =SUMIF('G4 Product Backlog'!$M$5:$M$27,A5,'G4 Product Backlog'!$J$5:$J$27) -> 73 | H5: 1, 4, 5, 6, 7, 8, 10, 11, 12, 14, 15, 16
A6: R2 | B6: Conexión, pruebas y cierre | C6: 6 a 7 | D6: 46330 | E6: Usar la app móvil conectada a la API, recibir alertas por filtros y ver su historial, entrar a la demostración en la nube y participar en la validación con usuarios. | F6: HU-04, HU-13, HU-14, HU-16, HU-19, HU-20, HU-21 | G6: =SUMIF('G4 Product Backlog'!$M$5:$M$27,A6,'G4 Product Backlog'!$J$5:$J$27) -> 45 | H6: 2, 3, 13, 18, 19
A7: R3 | B7: Backlog sin sprint asignado | C7: — | D7: — | E7: Historias que aún no tienen tareas en ningún sprint: verificación en dos pasos del administrador (HU-09) y seguridad y auditoría (HU-22). El equipo decide si entran antes de la entrega. La configuración de reglas (HU-11) se descartó. | F7: HU-09, HU-11, HU-22 | G7: =SUMIF('G4 Product Backlog'!$M$5:$M$27,A7,'G4 Product Backlog'!$J$5:$J$27) -> 18 | H7: 9, 17

Sheet H1 Sprints
A1: Calendario de sprints
A2: Un ciclo por sprint. Los sprints se cruzan en fechas porque los tres integrantes trabajan en paralelo. El proyecto comenzó el 20-08-2026; el Sprint 7 termina el 04-11 y la entrega es el 05-11-2026.
A4: Sprint | B4: Inicio | C4: Término | D4: Sprint Goal | E4: Release | F4: Puntos | G4: Tareas | H4: Hechas | I4: Estado
A5: 1 | B5: 46261 | C5: =B5+28 -> 46289 | D5: Documentación fase 1: definir el problema, la idea, los requisitos y la evaluación económica | E5: — | F5: =SUMIF('G4 Product Backlog'!$L$5:$L$27,A5,'G4 Product Backlog'!$J$5:$J$27) -> 0 | G5: =COUNTA('H3 Sprint 1'!B15:B20) -> 6 | H5: =COUNTIF('H3 Sprint 1'!H15:H20,"Hecho") -> 6 | I5: Terminado
A6: 2 | B6: 46272 | C6: =B6+26 -> 46298 | D6: Front-end móvil: construir las pantallas de la aplicación del inversionista | E6: — | F6: =SUMIF('G4 Product Backlog'!$L$5:$L$27,A6,'G4 Product Backlog'!$J$5:$J$27) -> 0 | G6: =COUNTA('H4 Sprint 2'!B15:B21) -> 7 | H6: =COUNTIF('H4 Sprint 2'!H15:H21,"Hecho") -> 7 | I6: Terminado
A7: 3 | B7: 46289 | C7: =B7+19 -> 46308 | D7: Complemento: prototipo, procesos AS-IS y TO-BE, vistas 4+1, modelo de datos y secciones complementarias del informe | E7: — | F7: =SUMIF('G4 Product Backlog'!$L$5:$L$27,A7,'G4 Product Backlog'!$J$5:$J$27) -> 0 | G7: =COUNTA('H5 Sprint 3'!B15:B24) -> 10 | H7: =COUNTIF('H5 Sprint 3'!H15:H24,"Hecho") -> 10 | I7: En curso
A8: 4 | B8: 46272 | C8: =B8+26 -> 46298 | D8: Backend: base de datos, API, base en la nube conectada con la página web y carga automática de remates | E8: R1 | F8: =SUMIF('G4 Product Backlog'!$L$5:$L$27,A8,'G4 Product Backlog'!$J$5:$J$27) -> 39 | G8: =COUNTA('H12 Sprint 4'!B15:B26) -> 12 | H8: =COUNTIF('H12 Sprint 4'!H15:H26,"Hecho") -> 12 | I8: Terminado
A9: 5 | B9: 46289 | C9: =B9+19 -> 46308 | D9: Front-end web: pantallas del inversionista, el administrador y el analista | E9: R1 | F9: =SUMIF('G4 Product Backlog'!$L$5:$L$27,A9,'G4 Product Backlog'!$J$5:$J$27) -> 34 | G9: =COUNTA('H13 Sprint 5'!B15:B28) -> 14 | H9: =COUNTIF('H13 Sprint 5'!H15:H28,"Hecho") -> 12 | I9: En curso
A10: 6 | B10: 46299 | C10: =B10+20 -> 46319 | D10: Conexión: conectar la app móvil (Android Studio) y la web con la API, y dejar la demostración en la nube | E10: R2 | F10: =SUMIF('G4 Product Backlog'!$L$5:$L$27,A10,'G4 Product Backlog'!$J$5:$J$27) -> 40 | G10: =COUNTA('H14 Sprint 6'!B15:B23) -> 9 | H10: =COUNTIF('H14 Sprint 6'!H15:H23,"Hecho") -> 5 | I10: En curso
A11: 7 | B11: 46320 | C11: =B11+10 -> 46330 | D11: Documentación fase 2 y cierre: pruebas, informe final y demostración | E11: R2 | F11: =SUMIF('G4 Product Backlog'!$L$5:$L$27,A11,'G4 Product Backlog'!$J$5:$J$27) -> 5 | G11: =COUNTA('H15 Sprint 7'!B15:B22) -> 8 | H11: =COUNTIF('H15 Sprint 7'!H15:H22,"Hecho") -> 1 | I11: Planificado
A14: Horas estimadas por integrante y sprint
D15: Integrante | E15: S1 | F15: S2 | G15: S3 | H15: S4 | I15: S5 | J15: S6 | K15: S7 | L15: Total | M15: Disponibles | N15: Uso
D16: Matías Negrete | E16: =SUMIF('H3 Sprint 1'!$D$15:$D$20,$D16,'H3 Sprint 1'!$E$15:$E$20) -> 34 | F16: =SUMIF('H4 Sprint 2'!$D$15:$D$21,$D16,'H4 Sprint 2'!$E$15:$E$21) -> 0 | G16: =SUMIF('H5 Sprint 3'!$D$15:$D$24,$D16,'H5 Sprint 3'!$E$15:$E$24) -> 28 | H16: =SUMIF('H12 Sprint 4'!$D$15:$D$26,$D16,'H12 Sprint 4'!$E$15:$E$26) -> 5 | I16: =SUMIF('H13 Sprint 5'!$D$15:$D$28,$D16,'H13 Sprint 5'!$E$15:$E$28) -> 0 | J16: =SUMIF('H14 Sprint 6'!$D$15:$D$23,$D16,'H14 Sprint 6'!$E$15:$E$23) -> 0 | K16: =SUMIF('H15 Sprint 7'!$D$15:$D$22,$D16,'H15 Sprint 7'!$E$15:$E$22) -> 14 | L16: =SUM(E16:K16) -> 81 | M16: ='G1 Squad'!$D$5*11 -> 110 | N16: =L16/M16 -> 0.73636364
D17: José Pizarro | E17: =SUMIF('H3 Sprint 1'!$D$15:$D$20,$D17,'H3 Sprint 1'!$E$15:$E$20) -> 0 | F17: =SUMIF('H4 Sprint 2'!$D$15:$D$21,$D17,'H4 Sprint 2'!$E$15:$E$21) -> 0 | G17: =SUMIF('H5 Sprint 3'!$D$15:$D$24,$D17,'H5 Sprint 3'!$E$15:$E$24) -> 0 | H17: =SUMIF('H12 Sprint 4'!$D$15:$D$26,$D17,'H12 Sprint 4'!$E$15:$E$26) -> 29 | I17: =SUMIF('H13 Sprint 5'!$D$15:$D$28,$D17,'H13 Sprint 5'!$E$15:$E$28) -> 28 | J17: =SUMIF('H14 Sprint 6'!$D$15:$D$23,$D17,'H14 Sprint 6'!$E$15:$E$23) -> 17 | K17: =SUMIF('H15 Sprint 7'!$D$15:$D$22,$D17,'H15 Sprint 7'!$E$15:$E$22) -> 9 | L17: =SUM(E17:K17) -> 83 | M17: ='G1 Squad'!$D$5*11 -> 110 | N17: =L17/M17 -> 0.75454545
D18: Basthian Bascuñan | E18: =SUMIF('H3 Sprint 1'!$D$15:$D$20,$D18,'H3 Sprint 1'!$E$15:$E$20) -> 0 | F18: =SUMIF('H4 Sprint 2'!$D$15:$D$21,$D18,'H4 Sprint 2'!$E$15:$E$21) -> 36 | G18: =SUMIF('H5 Sprint 3'!$D$15:$D$24,$D18,'H5 Sprint 3'!$E$15:$E$24) -> 0 | H18: =SUMIF('H12 Sprint 4'!$D$15:$D$26,$D18,'H12 Sprint 4'!$E$15:$E$26) -> 0 | I18: =SUMIF('H13 Sprint 5'!$D$15:$D$28,$D18,'H13 Sprint 5'!$E$15:$E$28) -> 11 | J18: =SUMIF('H14 Sprint 6'!$D$15:$D$23,$D18,'H14 Sprint 6'!$E$15:$E$23) -> 19 | K18: =SUMIF('H15 Sprint 7'!$D$15:$D$22,$D18,'H15 Sprint 7'!$E$15:$E$22) -> 14 | L18: =SUM(E18:K18) -> 80 | M18: ='G1 Squad'!$D$5*11 -> 110 | N18: =L18/M18 -> 0.72727273
D19: Total del sprint | E19: =SUM(E16:E18) -> 34 | F19: =SUM(F16:F18) -> 36 | G19: =SUM(G16:G18) -> 28 | H19: =SUM(H16:H18) -> 34 | I19: =SUM(I16:I18) -> 39 | J19: =SUM(J16:J18) -> 36 | K19: =SUM(K16:K18) -> 37 | L19: =SUM(E19:K19) -> 244 | M19: =SUM(M16:M18) -> 330 | N19: =L19/M19 -> 0.73939394
D20: Capacidad del sprint | E20: ='H3 Sprint 1'!$C$8 -> 41 | F20: ='H4 Sprint 2'!$C$8 -> 39 | G20: ='H5 Sprint 3'!$C$8 -> 29 | H20: ='H12 Sprint 4'!$C$8 -> 77 | I20: ='H13 Sprint 5'!$C$8 -> 57 | J20: ='H14 Sprint 6'!$C$8 -> 60 | K20: ='H15 Sprint 7'!$C$8 -> 47
D22: Disponibles: 10 horas semanales durante las 11 semanas del proyecto (20-08 al 05-11-2026). La capacidad de cada sprint cuenta solo a quienes trabajan en él; como los sprints se cruzan, la carga real de cada persona se revisa en la fila de su nombre.

Sheet H2 Definition of Done
A1: Definition of Done
A4: N.º | B4: Criterio | C4: Aplica a | D4: Cómo se verifica
A5: 1 | B5: El código está en GitHub y otro integrante revisó y aprobó el pull request | C5: Tarea | D5: Pull request aprobado
A6: 2 | B6: Cumple sus criterios de aceptación y se puede demostrar | C6: Historia | D6: Escenarios de la historia ejecutados
A7: 3 | B7: Tiene pruebas automatizadas del caso normal y de al menos un caso de error, y pasan | C7: Historia | D7: pytest / Playwright en verde
A8: 4 | B8: No deja defectos críticos ni altos abiertos | C8: Historia | D8: Registro de defectos
A9: 5 | B9: Funciona con los datos de prueba en el ambiente de pruebas | C9: Historia | D9: Ejecución en la base de prueba
A10: 6 | B10: La documentación quedó al día (OpenAPI, README o informe) | C10: Tarea | D10: Revisión en la Review
A11: 7 | B11: Respeta los criterios de seguridad y accesibilidad cuando aplican | C11: Historia | D11: Checklist de la sección E
A12: 8 | B12: El Product Owner la aceptó en la Sprint Review | C12: Incremento | D12: Validación A/R en la planilla

Sheet H3 Sprint 1
A1: Sprint 1 · Documentación fase 1 · 27-08 al 24-09-2026
A2: Ciclo: Documentación fase 1 · 29 días · trabaja: Matías Negrete · plan del 04-10-2026 (un ciclo por sprint; los sprints se cruzan en fechas)
B3: Sprint Goal | C3: Documentación fase 1: definir el problema, la idea, los requisitos y la evaluación económica
B4: Inicio | C4: 46261
B5: Término | C5: =IF(C4="","",C4+28) -> 46289
B6: Asistentes al Sprint Planning
B7: Historias comprometidas | C7: Sin historias de usuario: sprint de definición y documentación
B8: Capacidad del sprint (h) | C8: =ROUND(1*10*29/7,0) -> 41
B9: Horas estimadas | C9: =SUM(E15:E20) -> 34
B10: Tareas comprometidas al inicio | C10: =COUNTIF(G15:G20,C4) -> 6
B11: Fecha de corte | C11: 46289
A13: Sprint Backlog | J13: Avance día a día (✔ = tarea terminada) | AM13: PO
A14: N.º | B14: Tarea | C14: Relación | D14: Responsable | E14: Horas est. | F14: Horas reales | G14: Alta | H14: Estado | I14: Término | J14: =IF($C$4="","",$C$4+0) -> 46261 | K14: =IF($C$4="","",$C$4+1) -> 46262 | L14: =IF($C$4="","",$C$4+2) -> 46263 | M14: =IF($C$4="","",$C$4+3) -> 46264 | N14: =IF($C$4="","",$C$4+4) -> 46265 | O14: =IF($C$4="","",$C$4+5) -> 46266 | P14: =IF($C$4="","",$C$4+6) -> 46267 | Q14: =IF($C$4="","",$C$4+7) -> 46268 | R14: =IF($C$4="","",$C$4+8) -> 46269 | S14: =IF($C$4="","",$C$4+9) -> 46270 | T14: =IF($C$4="","",$C$4+10) -> 46271 | U14: =IF($C$4="","",$C$4+11) -> 46272 | V14: =IF($C$4="","",$C$4+12) -> 46273 | W14: =IF($C$4="","",$C$4+13) -> 46274 | X14: =IF($C$4="","",$C$4+14) -> 46275 | Y14: =IF($C$4="","",$C$4+15) -> 46276 | Z14: =IF($C$4="","",$C$4+16) -> 46277 | AA14: =IF($C$4="","",$C$4+17) -> 46278 | AB14: =IF($C$4="","",$C$4+18) -> 46279 | AC14: =IF($C$4="","",$C$4+19) -> 46280 | AD14: =IF($C$4="","",$C$4+20) -> 46281 | AE14: =IF($C$4="","",$C$4+21) -> 46282 | AF14: =IF($C$4="","",$C$4+22) -> 46283 | AG14: =IF($C$4="","",$C$4+23) -> 46284 | AH14: =IF($C$4="","",$C$4+24) -> 46285 | AI14: =IF($C$4="","",$C$4+25) -> 46286 | AJ14: =IF($C$4="","",$C$4+26) -> 46287 | AK14: =IF($C$4="","",$C$4+27) -> 46288 | AL14: =IF($C$4="","",$C$4+28) -> 46289 | AM14: PO (A/R)
A15: 1 | B15: Informe inicial: problema, idea de negocio y objetivos | C15: Documentación | D15: Matías Negrete | E15: 6 | G15: 46261 | H15: Hecho | I15: 46261 | J15: =IF($I15=J$14,"✔","") -> ✔ | K15: =IF($I15=K$14,"✔","") | L15: =IF($I15=L$14,"✔","") | M15: =IF($I15=M$14,"✔","") | N15: =IF($I15=N$14,"✔","") | O15: =IF($I15=O$14,"✔","") | P15: =IF($I15=P$14,"✔","") | Q15: =IF($I15=Q$14,"✔","") | ... AL15: =IF($I15=AL$14,"✔","") | AM15: A
A16: 2 | B16: Plan A y mapa mental | C16: Documentación | D16: Matías Negrete | E16: 4 | G16: 46261 | H16: Hecho | I16: 46263 | J16: =IF($I16=J$14,"✔","") | K16: =IF($I16=K$14,"✔","") | L16: =IF($I16=L$14,"✔","") -> ✔ | M16: =IF($I16=M$14,"✔","") | N16: =IF($I16=N$14,"✔","") | O16: =IF($I16=O$14,"✔","") | P16: =IF($I16=P$14,"✔","") | Q16: =IF($I16=Q$14,"✔","") | ... AL16: =IF($I16=AL$14,"✔","") | AM16: A
A17: 3 | B17: Mejora general del informe: actores, visión y alcance | C17: Documentación | D17: Matías Negrete | E17: 6 | G17: 46261 | H17: Hecho | I17: 46265 | J17: =IF($I17=J$14,"✔","") | K17: =IF($I17=K$14,"✔","") | L17: =IF($I17=L$14,"✔","") | M17: =IF($I17=M$14,"✔","") | N17: =IF($I17=N$14,"✔","") -> ✔ | O17: =IF($I17=O$14,"✔","") | P17: =IF($I17=P$14,"✔","") | Q17: =IF($I17=Q$14,"✔","") | ... AL17: =IF($I17=AL$14,"✔","") | AM17: A
A18: 4 | B18: Requisitos y justificación de las decisiones (secciones A, B, C y D) | C18: Documentación | D18: Matías Negrete | E18: 8 | G18: 46261 | H18: Hecho | I18: 46287 | J18: =IF($I18=J$14,"✔","") | K18: =IF($I18=K$14,"✔","") | L18: =IF($I18=L$14,"✔","") | M18: =IF($I18=M$14,"✔","") | N18: =IF($I18=N$14,"✔","") | O18: =IF($I18=O$14,"✔","") | P18: =IF($I18=P$14,"✔","") | Q18: =IF($I18=Q$14,"✔","") | ... AL18: =IF($I18=AL$14,"✔","") | AM18: A
A19: 5 | B19: Flujo de caja corregido: VAN, TIR y punto de equilibrio | C19: Evaluación económica | D19: Matías Negrete | E19: 5 | G19: 46261 | H19: Hecho | I19: 46288 | J19: =IF($I19=J$14,"✔","") | K19: =IF($I19=K$14,"✔","") | L19: =IF($I19=L$14,"✔","") | M19: =IF($I19=M$14,"✔","") | N19: =IF($I19=N$14,"✔","") | O19: =IF($I19=O$14,"✔","") | P19: =IF($I19=P$14,"✔","") | Q19: =IF($I19=Q$14,"✔","") | ... AL19: =IF($I19=AL$14,"✔","") | AM19: A
A20: 6 | B20: Respaldo de mercado: oferta de remates, morosidad y competencia | C20: Evaluación económica | D20: Matías Negrete | E20: 5 | G20: 46261 | H20: Hecho | I20: 46289 | J20: =IF($I20=J$14,"✔","") | K20: =IF($I20=K$14,"✔","") | L20: =IF($I20=L$14,"✔","") | M20: =IF($I20=M$14,"✔","") | N20: =IF($I20=N$14,"✔","") | O20: =IF($I20=O$14,"✔","") | P20: =IF($I20=P$14,"✔","") | Q20: =IF($I20=Q$14,"✔","") | ... AL20: =IF($I20=AL$14,"✔","") -> ✔ | AM20: A
B21: Total | E21: =SUM(E15:E20) -> 34 | F21: =SUM(F15:F20) -> 0 | H21: =COUNTIF(H15:H20,"Hecho")&" hechas" -> 6 hechas
A23: Burndown del sprint
A24: Día | B24: Fecha | C24: Ideal | D24: Pendientes
A25: 0 | B25: inicio | C25: =IF($C$10=0,"",ROUND($C$10-$C$10*A25/29,1)) -> 6 | D25: 6
A26: 1 | B26: 27-08 | C26: =IF($C$10=0,"",ROUND($C$10-$C$10*A26/29,1)) -> 5.8 | D26: 5
A27: 2 | B27: 28-08 | C27: =IF($C$10=0,"",ROUND($C$10-$C$10*A27/29,1)) -> 5.6 | D27: 5
A28: 3 | B28: 29-08 | C28: =IF($C$10=0,"",ROUND($C$10-$C$10*A28/29,1)) -> 5.4 | D28: 4
A29: 4 | B29: 30-08 | C29: =IF($C$10=0,"",ROUND($C$10-$C$10*A29/29,1)) -> 5.2 | D29: 4
A30: 5 | B30: 31-08 | C30: =IF($C$10=0,"",ROUND($C$10-$C$10*A30/29,1)) -> 5 | D30: 3
A31: 6 | B31: 01-09 | C31: =IF($C$10=0,"",ROUND($C$10-$C$10*A31/29,1)) -> 4.8 | D31: 3
A32: 7 | B32: 02-09 | C32: =IF($C$10=0,"",ROUND($C$10-$C$10*A32/29,1)) -> 4.6 | D32: 3
A33: 8 | B33: 03-09 | C33: =IF($C$10=0,"",ROUND($C$10-$C$10*A33/29,1)) -> 4.3 | D33: 3
A34: 9 | B34: 04-09 | C34: =IF($C$10=0,"",ROUND($C$10-$C$10*A34/29,1)) -> 4.1 | D34: 3
A35: 10 | B35: 05-09 | C35: =IF($C$10=0,"",ROUND($C$10-$C$10*A35/29,1)) -> 3.9 | D35: 3
A36: 11 | B36: 06-09 | C36: =IF($C$10=0,"",ROUND($C$10-$C$10*A36/29,1)) -> 3.7 | D36: 3
... A54: 29 | B54: 24-09 | C54: =IF($C$10=0,"",ROUND($C$10-$C$10*A54/29,1)) -> 0 | D54: 0

Sheet H4 Sprint 2
A1: Sprint 2 · Front-end móvil · 07-09 al 03-10-2026
A2: Ciclo: Front-end móvil · 27 días · trabaja: Basthian Bascuñan · plan del 04-10-2026 (un ciclo por sprint; los sprints se cruzan en fechas)
B3: Sprint Goal | C3: Front-end móvil: construir las pantallas de la aplicación del inversionista
B4: Inicio | C4: 46272
B5: Término | C5: =IF(C4="","",C4+26) -> 46298
B6: Asistentes al Sprint Planning
B7: Historias comprometidas | C7: Pantallas de HU-16; la historia se cierra en el Sprint 6, cuando la app se conecta con la API
B8: Capacidad del sprint (h) | C8: =ROUND(1*10*27/7,0) -> 39
B9: Horas estimadas | C9: =SUM(E15:E21) -> 36
B10: Tareas comprometidas al inicio | C10: =COUNTIF(G15:G21,C4) -> 7
B11: Fecha de corte | C11: 46298
A13: Sprint Backlog | J13: Avance día a día (✔ = tarea terminada) | AK13: PO
A14: N.º | B14: Tarea | C14: Relación | D14: Responsable | E14: Horas est. | F14: Horas reales | G14: Alta | H14: Estado | I14: Término | J14: =IF($C$4="","",$C$4+0) -> 46272 | K14: =IF($C$4="","",$C$4+1) -> 46273 | L14: =IF($C$4="","",$C$4+2) -> 46274 | M14: =IF($C$4="","",$C$4+3) -> 46275 | N14: =IF($C$4="","",$C$4+4) -> 46276 | O14: =IF($C$4="","",$C$4+5) -> 46277 | P14: =IF($C$4="","",$C$4+6) -> 46278 | Q14: =IF($C$4="","",$C$4+7) -> 46279 | R14: =IF($C$4="","",$C$4+8) -> 46280 | S14: =IF($C$4="","",$C$4+9) -> 46281 | T14: =IF($C$4="","",$C$4+10) -> 46282 | U14: =IF($C$4="","",$C$4+11) -> 46283 | V14: =IF($C$4="","",$C$4+12) -> 46284 | W14: =IF($C$4="","",$C$4+13) -> 46285 | X14: =IF($C$4="","",$C$4+14) -> 46286 | Y14: =IF($C$4="","",$C$4+15) -> 46287 | Z14: =IF($C$4="","",$C$4+16) -> 46288 | AA14: =IF($C$4="","",$C$4+17) -> 46289 | AB14: =IF($C$4="","",$C$4+18) -> 46290 | AC14: =IF($C$4="","",$C$4+19) -> 46291 | AD14: =IF($C$4="","",$C$4+20) -> 46292 | AE14: =IF($C$4="","",$C$4+21) -> 46293 | AF14: =IF($C$4="","",$C$4+22) -> 46294 | AG14: =IF($C$4="","",$C$4+23) -> 46295 | AH14: =IF($C$4="","",$C$4+24) -> 46296 | AI14: =IF($C$4="","",$C$4+25) -> 46297 | AJ14: =IF($C$4="","",$C$4+26) -> 46298 | AK14: PO (A/R)
A15: 1 | B15: App: estructura del proyecto, navegación y estilos del prototipo | C15: HU-16 | D15: Basthian Bascuñan | E15: 5 | G15: 46272 | H15: Hecho | I15: 46277 | J15: =IF($I15=J$14,"✔","") | K15: =IF($I15=K$14,"✔","") | L15: =IF($I15=L$14,"✔","") | M15: =IF($I15=M$14,"✔","") | N15: =IF($I15=N$14,"✔","") | O15: =IF($I15=O$14,"✔","") -> ✔ | P15: =IF($I15=P$14,"✔","") | Q15: =IF($I15=Q$14,"✔","") | ... AJ15: =IF($I15=AJ$14,"✔","") | AK15: A
A16: 2 | B16: App: pantallas de inicio de sesión y registro | C16: HU-16 · HU-01 | D16: Basthian Bascuñan | E16: 5 | G16: 46272 | H16: Hecho | I16: 46282 | J16: =IF($I16=J$14,"✔","") | K16: =IF($I16=K$14,"✔","") | L16: =IF($I16=L$14,"✔","") | M16: =IF($I16=M$14,"✔","") | N16: =IF($I16=N$14,"✔","") | O16: =IF($I16=O$14,"✔","") | P16: =IF($I16=P$14,"✔","") | Q16: =IF($I16=Q$14,"✔","") | ... AJ16: =IF($I16=AJ$14,"✔","") | AK16: A
A17: 3 | B17: App: pantalla de inicio | C17: HU-16 | D17: Basthian Bascuñan | E17: 4 | G17: 46272 | H17: Hecho | I17: 46286 | J17: =IF($I17=J$14,"✔","") | K17: =IF($I17=K$14,"✔","") | L17: =IF($I17=L$14,"✔","") | M17: =IF($I17=M$14,"✔","") | N17: =IF($I17=N$14,"✔","") | O17: =IF($I17=O$14,"✔","") | P17: =IF($I17=P$14,"✔","") | Q17: =IF($I17=Q$14,"✔","") | ... AJ17: =IF($I17=AJ$14,"✔","") | AK17: A
A18: 4 | B18: App: pantallas de guardados y notificaciones | C18: HU-16 · HU-07 | D18: Basthian Bascuñan | E18: 6 | G18: 46272 | H18: Hecho | I18: 46292 | J18: =IF($I18=J$14,"✔","") | K18: =IF($I18=K$14,"✔","") | L18: =IF($I18=L$14,"✔","") | M18: =IF($I18=M$14,"✔","") | N18: =IF($I18=N$14,"✔","") | O18: =IF($I18=O$14,"✔","") | P18: =IF($I18=P$14,"✔","") | Q18: =IF($I18=Q$14,"✔","") | ... AJ18: =IF($I18=AJ$14,"✔","") | AK18: A
A19: 5 | B19: App: pantalla de perfil | C19: HU-16 | D19: Basthian Bascuñan | E19: 4 | G19: 46272 | H19: Hecho | I19: 46295 | J19: =IF($I19=J$14,"✔","") | K19: =IF($I19=K$14,"✔","") | L19: =IF($I19=L$14,"✔","") | M19: =IF($I19=M$14,"✔","") | N19: =IF($I19=N$14,"✔","") | O19: =IF($I19=O$14,"✔","") | P19: =IF($I19=P$14,"✔","") | Q19: =IF($I19=Q$14,"✔","") | ... AJ19: =IF($I19=AJ$14,"✔","") | AK19: A
A20: 6 | B20: App: pantallas de catálogo y detalle con semáforo | C20: HU-16 · HU-02 | D20: Basthian Bascuñan | E20: 8 | F20: 7 | G20: 46272 | H20: Hecho | I20: 46298 | J20: =IF($I20=J$14,"✔","") | K20: =IF($I20=K$14,"✔","") | L20: =IF($I20=L$14,"✔","") | M20: =IF($I20=M$14,"✔","") | N20: =IF($I20=N$14,"✔","") | O20: =IF($I20=O$14,"✔","") | P20: =IF($I20=P$14,"✔","") | Q20: =IF($I20=Q$14,"✔","") | ... AJ20: =IF($I20=AJ$14,"✔","") -> ✔ | AK20: A
A21: 7 | B21: App: revisión del front-end completo en el emulador | C21: HU-16 | D21: Basthian Bascuñan | E21: 4 | G21: 46272 | H21: Hecho | I21: 46298 | J21: =IF($I21=J$14,"✔","") | K21: =IF($I21=K$14,"✔","") | L21: =IF($I21=L$14,"✔","") | M21: =IF($I21=M$14,"✔","") | N21: =IF($I21=N$14,"✔","") | O21: =IF($I21=O$14,"✔","") | P21: =IF($I21=P$14,"✔","") | Q21: =IF($I21=Q$14,"✔","") | ... AJ21: =IF($I21=AJ$14,"✔","") -> ✔ | AK21: A
B22: Total | E22: =SUM(E15:E21) -> 36 | F22: =SUM(F15:F21) -> 7 | H22: =COUNTIF(H15:H21,"Hecho")&" hechas" -> 7 hechas
A24: Burndown del sprint
A25: Día | B25: Fecha | C25: Ideal | D25: Pendientes
A26: 0 | B26: inicio | C26: =IF($C$10=0,"",ROUND($C$10-$C$10*A26/27,1)) -> 7 | D26: 7
A27: 1 | B27: 07-09 | C27: =IF($C$10=0,"",ROUND($C$10-$C$10*A27/27,1)) -> 6.7 | D27: 7
A28: 2 | B28: 08-09 | C28: =IF($C$10=0,"",ROUND($C$10-$C$10*A28/27,1)) -> 6.5 | D28: 7
A29: 3 | B29: 09-09 | C29: =IF($C$10=0,"",ROUND($C$10-$C$10*A29/27,1)) -> 6.2 | D29: 7
A30: 4 | B30: 10-09 | C30: =IF($C$10=0,"",ROUND($C$10-$C$10*A30/27,1)) -> 6 | D30: 7
A31: 5 | B31: 11-09 | C31: =IF($C$10=0,"",ROUND($C$10-$C$10*A31/27,1)) -> 5.7 | D31: 7
A32: 6 | B32: 12-09 | C32: =IF($C$10=0,"",ROUND($C$10-$C$10*A32/27,1)) -> 5.4 | D32: 6
A33: 7 | B33: 13-09 | C33: =IF($C$10=0,"",ROUND($C$10-$C$10*A33/27,1)) -> 5.2 | D33: 6
A34: 8 | B34: 14-09 | C34: =IF($C$10=0,"",ROUND($C$10-$C$10*A34/27,1)) -> 4.9 | D34: 6
A35: 9 | B35: 15-09 | C35: =IF($C$10=0,"",ROUND($C$10-$C$10*A35/27,1)) -> 4.7 | D35: 6
A36: 10 | B36: 16-09 | C36: =IF($C$10=0,"",ROUND($C$10-$C$10*A36/27,1)) -> 4.4 | D36: 6
A37: 11 | B37: 17-09 | C37: =IF($C$10=0,"",ROUND($C$10-$C$10*A37/27,1)) -> 4.1 | D37: 5
... A53: 27 | B53: 03-10 | C53: =IF($C$10=0,"",ROUND($C$10-$C$10*A53/27,1)) -> 0 | D53: 0

Sheet H5 Sprint 3
A1: Sprint 3 · Complemento · 24-09 al 13-10-2026
B3: Sprint Goal | C3: Complemento: prototipo, procesos AS-IS y TO-BE, vistas 4+1, modelo de datos y secciones complementarias del informe
B4: Inicio | C4: 46289
B5: Término | C5: =IF(C4="","",C4+19) -> 46308
B6: Asistentes al Sprint Planning
B7: Historias comprometidas | C7: Sin historias de usuario: sprint de diseño y documentación
B8: Capacidad del sprint (h) | C8: =ROUND(1*10*20/7,0) -> 29
B9: Horas estimadas | C9: =SUM(E15:E24) -> 28
B10: Tareas comprometidas al inicio | C10: =COUNTIF(G15:G24,C4) -> 8
B11: Fecha de corte | C11: 46299
A13: Sprint Backlog | J13: Avance día a día (✔ = tarea terminada) | AD13: PO
A14: N.º | B14: Tarea | C14: Relación | D14: Responsable | E14: Horas est. | F14: Horas reales | G14: Alta | H14: Estado | I14: Término | J14: =IF($C$4="","",$C$4+0) -> 46289 | K14: =IF($C$4="","",$C$4+1) -> 46290 | L14: =IF($C$4="","",$C$4+2) -> 46291 | M14: =IF($C$4="","",$C$4+3) -> 46292 | N14: =IF($C$4="","",$C$4+4) -> 46293 | O14: =IF($C$4="","",$C$4+5) -> 46294 | P14: =IF($C$4="","",$C$4+6) -> 46295 | Q14: =IF($C$4="","",$C$4+7) -> 46296 | R14: =IF($C$4="","",$C$4+8) -> 46297 | S14: =IF($C$4="","",$C$4+9) -> 46298 | T14: =IF($C$4="","",$C$4+10) -> 46299 | U14: =IF($C$4="","",$C$4+11) -> 46300 | V14: =IF($C$4="","",$C$4+12) -> 46301 | W14: =IF($C$4="","",$C$4+13) -> 46302 | X14: =IF($C$4="","",$C$4+14) -> 46303 | Y14: =IF($C$4="","",$C$4+15) -> 46304 | Z14: =IF($C$4="","",$C$4+16) -> 46305 | AA14: =IF($C$4="","",$C$4+17) -> 46306 | AB14: =IF($C$4="","",$C$4+18) -> 46307 | AC14: =IF($C$4="","",$C$4+19) -> 46308 | AD14: PO (A/R)
A15: 1 | B15: Prototipo de la app pública (11 pantallas) | C15: Diseño | D15: Matías Negrete | E15: 4 | G15: 46289 | H15: Hecho | I15: 46290 | J15: =IF($I15=J$14,"✔","") | K15: =IF($I15=K$14,"✔","") -> ✔ | L15: =IF($I15=L$14,"✔","") | M15: =IF($I15=M$14,"✔","") | N15: =IF($I15=N$14,"✔","") | O15: =IF($I15=O$14,"✔","") | P15: =IF($I15=P$14,"✔","") | Q15: =IF($I15=Q$14,"✔","") | ... AC15: =IF($I15=AC$14,"✔","") | AD15: A
A16: 2 | B16: Prototipo del administrador (16 pantallas) | C16: Diseño | D16: Matías Negrete | E16: 4 | G16: 46289 | H16: Hecho | I16: 46292 | J16: =IF($I16=J$14,"✔","") | K16: =IF($I16=K$14,"✔","") | L16: =IF($I16=L$14,"✔","") | M16: =IF($I16=M$14,"✔","") -> ✔ | N16: =IF($I16=N$14,"✔","") | O16: =IF($I16=O$14,"✔","") | P16: =IF($I16=P$14,"✔","") | Q16: =IF($I16=Q$14,"✔","") | ... AC16: =IF($I16=AC$14,"✔","") | AD16: A
A17: 3 | B17: Semáforo del informe en las pantallas y rol Analista | C17: Diseño | D17: Matías Negrete | E17: 2 | G17: 46289 | H17: Hecho | I17: 46293 | J17: =IF($I17=J$14,"✔","") | K17: =IF($I17=K$14,"✔","") | L17: =IF($I17=L$14,"✔","") | M17: =IF($I17=M$14,"✔","") | N17: =IF($I17=N$14,"✔","") -> ✔ | O17: =IF($I17=O$14,"✔","") | P17: =IF($I17=P$14,"✔","") | Q17: =IF($I17=Q$14,"✔","") | ... AC17: =IF($I17=AC$14,"✔","") | AD17: A
A18: 4 | B18: Procesos AS-IS y TO-BE en BPMN (20 diagramas) | C18: Diseño | D18: Matías Negrete | E18: 3 | G18: 46289 | H18: Hecho | I18: 46293 | J18: =IF($I18=J$14,"✔","") | K18: =IF($I18=K$14,"✔","") | L18: =IF($I18=L$14,"✔","") | M18: =IF($I18=M$14,"✔","") | N18: =IF($I18=N$14,"✔","") -> ✔ | O18: =IF($I18=O$14,"✔","") | P18: =IF($I18=P$14,"✔","") | Q18: =IF($I18=Q$14,"✔","") | ... AC18: =IF($I18=AC$14,"✔","") | AD18: A
A19: 5 | B19: Vistas 4+1 en draw.io (6 páginas) | C19: Diseño | D19: Matías Negrete | E19: 3 | G19: 46289 | H19: Hecho | I19: 46293 | J19: =IF($I19=J$14,"✔","") | K19: =IF($I19=K$14,"✔","") | L19: =IF($I19=L$14,"✔","") | M19: =IF($I19=M$14,"✔","") | N19: =IF($I19=N$14,"✔","") -> ✔ | O19: =IF($I19=O$14,"✔","") | P19: =IF($I19=P$14,"✔","") | Q19: =IF($I19=Q$14,"✔","") | ... AC19: =IF($I19=AC$14,"✔","") | AD19: A
A20: 6 | B20: Informe: UX/UI, seguridad e integraciones | C20: Documentación | D20: Matías Negrete | E20: 2 | G20: 46289 | H20: Hecho | I20: 46293 | J20: =IF($I20=J$14,"✔","") | K20: =IF($I20=K$14,"✔","") | L20: =IF($I20=L$14,"✔","") | M20: =IF($I20=M$14,"✔","") | N20: =IF($I20=N$14,"✔","") -> ✔ | O20: =IF($I20=O$14,"✔","") | P20: =IF($I20=P$14,"✔","") | Q20: =IF($I20=Q$14,"✔","") | ... AC20: =IF($I20=AC$14,"✔","") | AD20: A
A21: 7 | B21: Informe: secciones F a M y Conclusión | C21: Documentación | D21: Matías Negrete | E21: 2 | G21: 46289 | H21: Hecho | I21: 46294 | J21: =IF($I21=J$14,"✔","") | K21: =IF($I21=K$14,"✔","") | L21: =IF($I21=L$14,"✔","") | M21: =IF($I21=M$14,"✔","") | N21: =IF($I21=N$14,"✔","") | O21: =IF($I21=O$14,"✔","") -> ✔ | P21: =IF($I21=P$14,"✔","") | Q21: =IF($I21=Q$14,"✔","") | ... AC21: =IF($I21=AC$14,"✔","") | AD21: A
A22: 8 | B22: Modelo de base de datos: diagrama ER y script SQL de referencia | C22: Documentación | D22: Matías Negrete | E22: 2 | G22: 46289 | H22: Hecho | I22: 46294 | J22: =IF($I22=J$14,"✔","") | K22: =IF($I22=K$14,"✔","") | L22: =IF($I22=L$14,"✔","") | M22: =IF($I22=M$14,"✔","") | N22: =IF($I22=N$14,"✔","") | O22: =IF($I22=O$14,"✔","") -> ✔ | P22: =IF($I22=P$14,"✔","") | Q22: =IF($I22=Q$14,"✔","") | ... AC22: =IF($I22=AC$14,"✔","") | AD22: A
A23: 9 | B23: Informe: secciones E, F, G y H con planilla de tablas | C23: Documentación | D23: Matías Negrete | E23: 3 | G23: 46295 | H23: Hecho | I23: 46299 | J23: =IF($I23=J$14,"✔","") | K23: =IF($I23=K$14,"✔","") | L23: =IF($I23=L$14,"✔","") | M23: =IF($I23=M$14,"✔","") | N23: =IF($I23=N$14,"✔","") | O23: =IF($I23=O$14,"✔","") | P23: =IF($I23=P$14,"✔","") | Q23: =IF($I23=Q$14,"✔","") | ... AC23: =IF($I23=AC$14,"✔","") | AD23: A
A24: 10 | B24: Documentos de dirección del proyecto (12 plantillas: acta, alcance, EDT, presupuesto y planes) | C24: Documentación | D24: Matías Negrete | E24: 3 | G24: 46298 | H24: Hecho | J24: =IF($I24=J$14,"✔","") | K24: =IF($I24=K$14,"✔","") | L24: =IF($I24=L$14,"✔","") | M24: =IF($I24=M$14,"✔","") | N24: =IF($I24=N$14,"✔","") | O24: =IF($I24=O$14,"✔","") | P24: =IF($I24=P$14,"✔","") | Q24: =IF($I24=Q$14,"✔","") | ... AC24: =IF($I24=AC$14,"✔","") | AD24: A
B25: Total | E25: =SUM(E15:E24) -> 28 | F25: =SUM(F15:F24) -> 0 | H25: =COUNTIF(H15:H24,"Hecho")&" hechas" -> 10 hechas
A27: Burndown del sprint
A28: Día | B28: Fecha | C28: Ideal | D28: Pendientes
A29: 0 | B29: inicio | C29: =IF($C$10=0,"",ROUND($C$10-$C$10*A29/20,1)) -> 8 | D29: 8
A30: 1 | B30: 24-09 | C30: =IF($C$10=0,"",ROUND($C$10-$C$10*A30/20,1)) -> 7.6 | D30: 8
A31: 2 | B31: 25-09 | C31: =IF($C$10=0,"",ROUND($C$10-$C$10*A31/20,1)) -> 7.2 | D31: 7
A32: 3 | B32: 26-09 | C32: =IF($C$10=0,"",ROUND($C$10-$C$10*A32/20,1)) -> 6.8 | D32: 7
A33: 4 | B33: 27-09 | C33: =IF($C$10=0,"",ROUND($C$10-$C$10*A33/20,1)) -> 6.4 | D33: 6
A34: 5 | B34: 28-09 | C34: =IF($C$10=0,"",ROUND($C$10-$C$10*A34/20,1)) -> 6 | D34: 2
A35: 6 | B35: 29-09 | C35: =IF($C$10=0,"",ROUND($C$10-$C$10*A35/20,1)) -> 5.6 | D35: 0
A36: 7 | B36: 30-09 | C36: =IF($C$10=0,"",ROUND($C$10-$C$10*A36/20,1)) -> 5.2 | D36: 1
A37: 8 | B37: 01-10 | C37: =IF($C$10=0,"",ROUND($C$10-$C$10*A37/20,1)) -> 4.8 | D37: 1
A38: 9 | B38: 02-10 | C38: =IF($C$10=0,"",ROUND($C$10-$C$10*A38/20,1)) -> 4.4 | D38: 1
A39: 10 | B39: 03-10 | C39: =IF($C$10=0,"",ROUND($C$10-$C$10*A39/20,1)) -> 4 | D39: 2
A40: 11 | B40: 04-10 | C40: =IF($C$10=0,"",ROUND($C$10-$C$10*A40/20,1)) -> 3.6 | D40: 1
A41: 12 | B41: 05-10 | C41: =IF($C$10=0,"",ROUND($C$10-$C$10*A41/20,1)) -> 3.2
A42: 13 | B42: 06-10 | C42: =IF($C$10=0,"",ROUND($C$10-$C$10*A42/20,1)) -> 2.8
A43: 14 | B43: 07-10 | C43: =IF($C$10=0,"",ROUND($C$10-$C$10*A43/20,1)) -> 2.4
A44: 15 | B44: 08-10 | C44: =IF($C$10=0,"",ROUND($C$10-$C$10*A44/20,1)) -> 2
A45: 16 | B45: 09-10 | C45: =IF($C$10=0,"",ROUND($C$10-$C$10*A45/20,1)) -> 1.6
A46: 17 | B46: 10-10 | C46: =IF($C$10=0,"",ROUND($C$10-$C$10*A46/20,1)) -> 1.2
A47: 18 | B47: 11-10 | C47: =IF($C$10=0,"",ROUND($C$10-$C$10*A47/20,1)) -> 0.8
A48: 19 | B48: 12-10 | C48: =IF($C$10=0,"",ROUND($C$10-$C$10*A48/20,1)) -> 0.4
A49: 20 | B49: 13-10 | C49: =IF($C$10=0,"",ROUND($C$10-$C$10*A49/20,1)) -> 0

Sheet H6 Scrum Board
A1: Scrum Board · sprints en curso (3, 5, 6) al 04-10-2026
A4: Por hacer (11) | B4: En curso (5) | C4: Hecho (17)
A5: S5 · 8. Panel del administrador: resumen de los últimos 7 días Entregable 15 · José P. | B5: S3 · 10. Documentos de dirección del proyecto (12 plantillas: acta, alcance, EDT, presupuesto y planes) Documentación · Matías N. | C5: S3 · 1. Prototipo de la app pública (11 pantallas) Diseño · Matías N. · 25-09
A6: S5 · 9. Anuncios del administrador y notificaciones del inversionista HU-18 · HU-14 · José P. | B6: S5 · 10. Perfil del inversionista y cambio de contraseña HU-12 · José P. | C6: S3 · 2. Prototipo del administrador (16 pantallas) Diseño · Matías N. · 27-09
A7: S5 · 13. Encabezado de la web en celular DEF-07 · José P. | B7: S5 · 11. Mapa de remates por comuna HU-15 · Basthian B. | C7: S3 · 3. Semáforo del informe en las pantallas y rol Analista Diseño · Matías N. · 28-09
A8: S5 · 14. Sprint Review Equipo · José P. | B8: S5 · 12. Panel del analista: resumen, subastas, usuarios y alcance HU-17 · Basthian B. | C8: S3 · 4. Procesos AS-IS y TO-BE en BPMN (20 diagramas) Diseño · Matías N. · 28-09
A9: S6 · 2. App: abrir el proyecto en Android Studio y conectarlo con la API (emulador y celular) HU-16 · HU-04 · Basthian B. | B9: S6 · 8. Pruebas de integración: registro, login, catálogo y semáforo (pytest + httpx) HU-19 · José P. | C9: S3 · 5. Vistas 4+1 en draw.io (6 páginas) Diseño · Matías N. · 28-09
A10: S6 · 3. App: registro e inicio de sesión contra la API (token) HU-16 · HU-01 · Basthian B. | C10: S3 · 6. Informe: UX/UI, seguridad e integraciones Documentación · Matías N. · 28-09
A11: S6 · 4. App: catálogo y detalle con los datos de la API HU-16 · HU-02 · Basthian B. | C11: S3 · 7. Informe: secciones F a M y Conclusión Documentación · Matías N. · 29-09
A12: S6 · 5. App: guardados y notificaciones desde la API HU-16 · HU-07 · Basthian B. | C12: S3 · 8. Modelo de base de datos: diagrama ER y script SQL de referencia Documentación · Matías N. · 29-09
A13: S6 · 6. Web: alertas desde la API (reemplaza los datos de prueba del navegador) HU-13 · José P. | C13: S3 · 9. Informe: secciones E, F, G y H con planilla de tablas Documentación · Matías N. · 04-10
A14: S6 · 7. Despliegue de demostración (API, base de datos y web) HU-20 · José P. | C14: S5 · 1. Sesión en la web: login, token y /auth/me HU-01 · José P. · 29-09
A15: S6 · 9. Sprint Review Equipo · José P. | C15: S5 · 2. Catálogo con filtros y detalle de propiedad en la web HU-02 · HU-06 · DEF-04 · José P. · 29-09
C16: S5 · 3. Guardados por API en la web (/favoritos) HU-07 · José P. · 29-09
C17: S5 · 4. Menú del administrador: Panel, Publicaciones, Opiniones y Anuncios HU-23 · José P. · 29-09
C18: S5 · 5. Opiniones: envío del inversionista y respuesta del administrador HU-18 · José P. · 03-10
C19: S5 · 6. Publicaciones del administrador con vistas y guardados HU-23 · José P. · 30-09
C20: S5 · 7. Catálogo: ordenar por fecha de remate (más próximo primero) HU-06 · José P. · 03-10
C21: S6 · 1. Corrección de DEF-03: crear la propiedad en una sola transacción HU-03 · José P. · 04-10

Sheet H7 Daily
A1: Daily Meetings · del 24-09 al 13-10-2026
A4: Fecha | B4: Día | C4: Avance registrado (tareas terminadas) | D4: Asistentes | E4: ¿Qué se hará hoy? | F4: Impedimentos | G4: Acuerdos
A5: 46289 | B5: jue | C5: • S1 · Respaldo de mercado: oferta de remates, morosidad y competencia
A6: 46290 | B6: vie | C6: • S3 · Prototipo de la app pública (11 pantallas)
A7: 46291 | B7: sáb | C7: Sin tareas terminadas
A8: 46292 | B8: dom | C8: • S2 · App: pantallas de guardados y notificaciones • S3 · Prototipo del administrador (16 pantallas)
A9: 46293 | B9: lun | C9: • S3 · Semáforo del informe en las pantallas y rol Analista • S3 · Procesos AS-IS y TO-BE en BPMN (20 diagramas) • S3 · Vistas 4+1 en draw.io (6 páginas) • S3 · Informe: UX/UI, seguridad e integraciones • S4 · Semáforo: diagnóstico de las 7 propiedades de prueba y umbrales de estado legal
A10: 46294 | B10: mar | C10: • S3 · Informe: secciones F a M y Conclusión • S3 · Modelo de base de datos: diagrama ER y script SQL de referencia • S4 · Registro de vistas: tabla property_views y POST /vista • S5 · Sesión en la web: login, token y /auth/me • S5 · Catálogo con filtros y detalle de propiedad en la web • S5 · Guardados por API en la web (/favoritos) • S5 · Menú del administrador: Panel, Publicaciones, Opiniones y Anuncios
A11: 46295 | B11: mié | C11: • S2 · App: pantalla de perfil • S4 · API del administrador: publicaciones con vistas y guardados, detalle y descripción • S4 · Fotos: tabla property_photos y API para subir, borrar, ordenar y mostrar • S5 · Publicaciones del administrador con vistas y guardados
A12: 46296 | B12: jue | C12: • S4 · Correcciones del guardado: evaluación al guardar (DEF-01) y duplicados (DEF-02)
A13: 46297 | B13: vie | C13: • S4 · Base de datos en la nube conectada con la página web
A14: 46298 | B14: sáb | C14: • S2 · App: pantallas de catálogo y detalle con semáforo • S2 · App: revisión del front-end completo en el emulador • S4 · Base de datos y API: fecha del remate y tipo extrajudicial • S4 · Carga automática de remates (scrapeo de rematesinmobiliarios.cl), sin duplicados • S4 · Sprint Review de los sprints 2 y 4 • S5 · Opiniones: envío del inversionista y respuesta del administrador • S5 · Catálogo: ordenar por fecha de remate (más próximo primero)
A15: 46299 | B15: dom | C15: • S3 · Informe: secciones E, F, G y H con planilla de tablas • S6 · Corrección de DEF-03: crear la propiedad en una sola transacción
A16: 46300 | B16: lun
A17: 46301 | B17: mar
A18: 46302 | B18: mié
A19: 46303 | B19: jue
A20: 46304 | B20: vie
A21: 46305 | B21: sáb
A22: 46306 | B22: dom
A23: 46307 | B23: lun
A24: 46308 | B24: mar

Sheet H8 Impediment Log
A1: Impediment Log
A4: ID | B4: Detectado | C4: Impedimento | D4: Afecta a | E4: Responsable | F4: Acción | G4: Estado | H4: Cierre
A5: IMP-01 | B5: 46293 | C5: El SII no muestra la superficie del departamento de prueba (rol vigente aún sin visualización en Mapas SII); el m² no se puede automatizar desde esa fuente. | D5: HU-03 · HU-10 | E5: Matías Negrete | F5: Tomar el m² del aviso cuando aparezca, que lo cargue el equipo o que lo ingrese el inversionista; decidir en la Sprint Review del 13-10. | G5: Abierto
A6: IMP-02 | B6: 46293 | C6: El principal portal de venta de propiedades bloquea la lectura automática (robots.txt y protección anti-bots): no hay comparables automáticos. | D6: HU-03 | E6: Matías Negrete | F6: Evaluar para el MVP una tabla de valor en UF por m² por comuna, actualizada a mano con informes públicos. | G6: En evaluación
A7: IMP-03 | B7: 46293 | C7: Dos propiedades de prueba quedaron sin evaluación después de guardarlas. | D7: HU-03 | E7: José Pizarro | F7: Registrado como DEF-01; corregido el 01-10 (falta la re-prueba del caso CP-12). | G7: Cerrado | H7: 46296
A8: IMP-04 | B8: 46293 | C8: rematesinmobiliarios.cl, la fuente de la carga automática, no contiene la data explicita, ademas no constesta la solicutd enviada sobre la autorizacion para realizar el scrapeo | D8: HU-10 | E8: Matías Negrete | F8: Dejar evidencia de la solicitud, y darse a explicar a detalles los fines que tiene esta intervencion. | G8: Cerrado | H8: 46293

Sheet H9 Evidencias
A1: Evidencias técnicas
A4: Sprint | B4: Fecha | C4: Evidencia | D4: Tipo | E4: Archivo o ubicación
A5: 1 | B5: 46261 | C5: Informe: versión inicial | D5: Documento | E5: Informe del proyecto (27-08)
A6: 1 | B6: 46263 | C6: Informe: plan A y mapa mental | D6: Documento | E6: Informe del proyecto (29-08)
A7: 1 | B7: 46265 | C7: Informe: mejora general | D7: Documento | E7: Informe del proyecto (31-08)
A8: 1 | B8: 46287 | C8: Informe: justificación de requisitos y decisiones | D8: Documento | E8: Informe del proyecto (22-09)
A9: 1 | B9: 46288 | C9: Flujo de caja corregido: VAN +$1.512.012, TIR 20,8 %, equilibrio 17 clientes | D9: Planilla | E9: Flujo de caja HouseGreen
A10: 1 | B10: 46289 | C10: Respaldo de mercado: 1.152 remates activos, morosidad 2,3 %, competencia | D10: Documento | E10: Respaldo de mercado HouseGreen
A11: 3 | B11: 46290 | C11: Prototipo de la app pública (11 pantallas) | D11: Diseño | E11: HouseGreen-pantallas-app.zip
A12: 3 | B12: 46292 | C12: Prototipo del administrador (16 pantallas) | D12: Diseño | E12: HouseGreen-pantallas-app.zip
A13: 3 | B13: 46293 | C13: Procesos AS-IS y TO-BE (20 diagramas BPMN) | D13: Diagrama | E13: HouseGreen-procesos-AS-IS-TO-BE.zip
A14: 3 | B14: 46293 | C14: Vistas 4+1 (6 páginas) | D14: Diagrama | E14: HouseGreen-vistas-4+1.drawio
A15: 4 | B15: 46293 | C15: Umbrales de estado legal corregidos: 1, 2, 3 y 4 gravámenes dan 2, 1, 1 y 0 puntos | D15: Base de datos | E15: Base del proyecto (semaforo_thresholds)
A16: 5 | B16: 46294 | C16: GET /auth/me y sesión en la web (AuthContext, ProtectedRoute) | D16: Código | E16: housegreen-api · housegreen-web/src
... A29: 2 | B29: 46298 | C29: Front-end de la aplicación móvil terminado | D29: Código | E29: Proyecto de la app (Android Studio)

Sheet H10 Review y feedback
A2: Sección H · Ejecución iterativa (sprints) · estado al 04-10-2026
A4: Sprint | B4: Fecha | C4: Asistentes | D4: Incremento presentado | E4: Decisiones | F4: PO (A/R)
A5: 1 | B5: 46289 | D5: Informe de la fase 1: problema, mapa mental, actores, visión, requisitos justificados, flujo de caja corregido y respaldo de mercado | F5: A
A6: 2 y 4 | B6: 46298 | D6: Front-end de la app terminado; base de datos en la nube conectada con la página web (02-10), API del administrador, fotos y carga automática de 444 remates (03-10) | E6: Por decidir: origen del m² (IMP-01), comparables (IMP-02) y autorización de la fuente de datos (IMP-04)
A7: 3 y 5 | B7: 46308 | D7: Prototipo (31 pantallas), BPMN, vistas 4+1, modelo de datos e informe; en la web: sesión, catálogo, detalle, guardados y opiniones
A8: 6 | B8: 46319 | D8: App y web conectadas con la API; demostración en la nube
A9: 7 | B9: 46330 | D9: Pruebas, informe final y presentación
B11: Feedback del mandante y los usuarios
B12: Fecha | C12: Quién | D12: Comentario | E12: Acción en el backlog | F12: Estado
B13: 46294 | C13: Product Owner | D13: El administrador no crea propiedades (entran por la ingesta) y solo edita fotos y descripción; su menú no incluye las reglas del semáforo. | E13: Se descarta la tarea del formulario (DEF-05); se revisa el alcance de HU-11 y RF-10 | F13: Aplicado
B14: 46294 | C14: Product Owner | D14: Semáforo preliminar: estado legal y deudas se muestran «Por verificar» con enlaces a las fuentes hasta que se carguen. | E14: Actualizar la regla de completitud en el informe | F14: Pendiente
B15: 46294 | C15: Product Owner | D15: El administrador debe ver quién vio y quién guardó cada publicación para enviarles anuncios. | E15: Nueva historia HU-23 | F15: Aplicado

Sheet H11 Retrospectivas
A1: Retrospectivas
A4: Retrospectiva del Sprint 1 (Documentación fase 1) | B4: Respuesta del equipo
A5: ¿Qué salió bien en la iteración? | B5: 1. Se definió el problema y la idea en la primera semana: tres versiones del informe entre el 27 y el 31-08. 2. Requisitos justificados con fuentes (22-09). 3. Se corrigió el flujo de caja.
A6: ¿Qué no salió bien en la iteración? | B6: 1. No se registraron las tareas ni las horas de cada día, por lo que el avance se reconstruyó con las versiones del informe. 2. La planilla del flujo de caja tenía un error en el cálculo del VAN que se detectó al final.
A7: ¿Qué mejoras vamos a implementar en la próxima iteración? | B7: 1. Registrar cada tarea con su fecha de término y actualizar el tablero en la Daily. 2. Que otra persona revise las fórmulas antes de entregar. 3. Cerrar la investigación antes del último día del sprint.
A9: Retrospectiva de los sprints 2 y 4 (Front-end móvil y Backend) | B9: Respuesta del equipo
A10: ¿Qué salió bien en la iteración? | B10: 1. Avance del código paso a paso, probando cada cambio antes de seguir. 2. Los errores encontrados quedaron registrados como defectos. 3. La base de datos quedó conectada con la página web (02-10) y la carga automática trajo 444 remates reales (03-10).
A11: ¿Qué no salió bien en la iteración? | B11: 1. Aún no hay pruebas automatizadas. 2. Las tareas de desarrollo no se registraron día a día: sus fechas se reconstruyeron al cierre.
A12: ¿Qué mejoras vamos a implementar en la próxima iteración? | B12: 1. Planificar también los pasos de desarrollo en el Sprint Planning. 2. Escribir la prueba automática junto con cada cambio. 3. Registrar cada tarea el día en que se termina.
A14: Retrospectiva del Sprint 3 (Complemento), al 04-10 | B14: Respuesta del equipo
A15: ¿Qué salió bien en la iteración? | B15: 1. Diseño completo en cinco días: 31 pantallas, 20 diagramas BPMN y 6 vistas 4+1.
A16: ¿Qué no salió bien en la iteración? | B16: 1. El semáforo del prototipo no coincidía con el del informe y hubo que rehacer pantallas (28-09). 2. Entraron tareas no planificadas al sprint.
A17: ¿Qué mejoras vamos a implementar en la próxima iteración? | B17: 1. Acordar las reglas de negocio antes de diseñar pantallas.

Sheet H12 Sprint 4
A1: Sprint 4 · Backend · 07-09 al 03-10-2026
A2: Ciclo: Backend · 27 días · trabajan: José Pizarro y Matías Negrete · plan del 04-10-2026 (un ciclo por sprint; los sprints se cruzan en fechas)
B3: Sprint Goal | C3: Backend: base de datos, API, base en la nube conectada con la página web y carga automática de remates
B4: Inicio | C4: 46272
B5: Término | C5: =IF(C4="","",C4+26) -> 46298
B6: Asistentes al Sprint Planning
B7: Historias comprometidas | C7: HU-01, HU-03, HU-05, HU-08, HU-10 y HU-23
B8: Capacidad del sprint (h) | C8: =ROUND(2*10*27/7,0) -> 77
B9: Horas estimadas | C9: =SUM(E15:E26) -> 34
B10: Tareas comprometidas al inicio | C10: =COUNTIF(G15:G26,C4) -> 12
B11: Fecha de corte | C11: 46298
A13: Sprint Backlog | J13: Avance día a día (✔ = tarea terminada) | AK13: PO
A14: N.º | B14: Tarea | C14: Relación | D14: Responsable | E14: Horas est. | F14: Horas reales | G14: Alta | H14: Estado | I14: Término | J14: =IF($C$4="","",$C$4+0) -> 46272 | K14: =IF($C$4="","",$C$4+1) -> 46273 | L14: =IF($C$4="","",$C$4+2) -> 46274 | M14: =IF($C$4="","",$C$4+3) -> 46275 | N14: =IF($C$4="","",$C$4+4) -> 46276 | O14: =IF($C$4="","",$C$4+5) -> 46277 | P14: =IF($C$4="","",$C$4+6) -> 46278 | Q14: =IF($C$4="","",$C$4+7) -> 46279 | R14: =IF($C$4="","",$C$4+8) -> 46280 | S14: =IF($C$4="","",$C$4+9) -> 46281 | T14: =IF($C$4="","",$C$4+10) -> 46282 | U14: =IF($C$4="","",$C$4+11) -> 46283 | V14: =IF($C$4="","",$C$4+12) -> 46284 | W14: =IF($C$4="","",$C$4+13) -> 46285 | X14: =IF($C$4="","",$C$4+14) -> 46286 | Y14: =IF($C$4="","",$C$4+15) -> 46287 | Z14: =IF($C$4="","",$C$4+16) -> 46288 | AA14: =IF($C$4="","",$C$4+17) -> 46289 | AB14: =IF($C$4="","",$C$4+18) -> 46290 | AC14: =IF($C$4="","",$C$4+19) -> 46291 | AD14: =IF($C$4="","",$C$4+20) -> 46292 | AE14: =IF($C$4="","",$C$4+21) -> 46293 | AF14: =IF($C$4="","",$C$4+22) -> 46294 | AG14: =IF($C$4="","",$C$4+23) -> 46295 | AH14: =IF($C$4="","",$C$4+24) -> 46296 | AI14: =IF($C$4="","",$C$4+25) -> 46297 | AJ14: =IF($C$4="","",$C$4+26) -> 46298 | AK14: PO (A/R)
A15: 1 | B15: Base de datos: modelo de datos y reglas del semáforo | C15: Técnica | D15: Matías Negrete | E15: 3 | G15: 46272 | H15: Hecho | I15: 46279 | J15: =IF($I15=J$14,"✔","") | K15: =IF($I15=K$14,"✔","") | L15: =IF($I15=L$14,"✔","") | M15: =IF($I15=M$14,"✔","") | N15: =IF($I15=N$14,"✔","") | O15: =IF($I15=O$14,"✔","") | P15: =IF($I15=P$14,"✔","") | Q15: =IF($I15=Q$14,"✔","") -> ✔ | ... AJ15: =IF($I15=AJ$14,"✔","") | AK15: A
A16: 2 | B16: Base de datos: creación de las tablas y carga de las comunas en PostgreSQL | C16: Técnica | D16: José Pizarro | E16: 3 | G16: 46272 | H16: Hecho | I16: 46279 | J16: =IF($I16=J$14,"✔","") | K16: =IF($I16=K$14,"✔","") | L16: =IF($I16=L$14,"✔","") | M16: =IF($I16=M$14,"✔","") | N16: =IF($I16=N$14,"✔","") | O16: =IF($I16=O$14,"✔","") | P16: =IF($I16=P$14,"✔","") | Q16: =IF($I16=Q$14,"✔","") -> ✔ | ... AJ16: =IF($I16=AJ$14,"✔","") | AK16: A
A17: 3 | B17: API: registro, inicio de sesión, propiedades y comunas | C17: HU-01 · HU-02 | D17: José Pizarro | E17: 4 | G17: 46272 | H17: Hecho | I17: 46286 | J17: =IF($I17=J$14,"✔","") | K17: =IF($I17=K$14,"✔","") | L17: =IF($I17=L$14,"✔","") | M17: =IF($I17=M$14,"✔","") | N17: =IF($I17=N$14,"✔","") | O17: =IF($I17=O$14,"✔","") | P17: =IF($I17=P$14,"✔","") | Q17: =IF($I17=Q$14,"✔","") | ... AJ17: =IF($I17=AJ$14,"✔","") | AK17: A
A18: 4 | B18: Semáforo: diagnóstico de las 7 propiedades de prueba y umbrales de estado legal | C18: HU-03 · DEF-06 | D18: Matías Negrete | E18: 2 | G18: 46272 | H18: Hecho | I18: 46293 | J18: =IF($I18=J$14,"✔","") | K18: =IF($I18=K$14,"✔","") | L18: =IF($I18=L$14,"✔","") | M18: =IF($I18=M$14,"✔","") | N18: =IF($I18=N$14,"✔","") | O18: =IF($I18=O$14,"✔","") | P18: =IF($I18=P$14,"✔","") | Q18: =IF($I18=Q$14,"✔","") | ... AJ18: =IF($I18=AJ$14,"✔","") | AK18: A
A19: 5 | B19: Registro de vistas: tabla property_views y POST /vista | C19: HU-23 | D19: José Pizarro | E19: 2 | G19: 46272 | H19: Hecho | I19: 46294 | J19: =IF($I19=J$14,"✔","") | K19: =IF($I19=K$14,"✔","") | L19: =IF($I19=L$14,"✔","") | M19: =IF($I19=M$14,"✔","") | N19: =IF($I19=N$14,"✔","") | O19: =IF($I19=O$14,"✔","") | P19: =IF($I19=P$14,"✔","") | Q19: =IF($I19=Q$14,"✔","") | ... AJ19: =IF($I19=AJ$14,"✔","") | AK19: A
A20: 6 | B20: API del administrador: publicaciones con vistas y guardados, detalle y descripción | C20: HU-23 · HU-08 | D20: José Pizarro | E20: 3 | G20: 46272 | H20: Hecho | I20: 46295 | J20: =IF($I20=J$14,"✔","") | K20: =IF($I20=K$14,"✔","") | L20: =IF($I20=L$14,"✔","") | M20: =IF($I20=M$14,"✔","") | N20: =IF($I20=N$14,"✔","") | O20: =IF($I20=O$14,"✔","") | P20: =IF($I20=P$14,"✔","") | Q20: =IF($I20=Q$14,"✔","") | ... AJ20: =IF($I20=AJ$14,"✔","") | AK20: A
A21: 7 | B21: Fotos: tabla property_photos y API para subir, borrar, ordenar y mostrar | C21: HU-08 · HU-02 | D21: José Pizarro | E21: 3 | G21: 46272 | H21: Hecho | I21: 46295 | J21: =IF($I21=J$14,"✔","") | K21: =IF($I21=K$14,"✔","") | L21: =IF($I21=L$14,"✔","") | M21: =IF($I21=M$14,"✔","") | N21: =IF($I21=N$14,"✔","") | O21: =IF($I21=O$14,"✔","") | P21: =IF($I21=P$14,"✔","") | Q21: =IF($I21=Q$14,"✔","") | ... AJ21: =IF($I21=AJ$14,"✔","") | AK21: A
A22: 8 | B22: Correcciones del guardado: evaluación al guardar (DEF-01) y duplicados (DEF-02) | C22: HU-03 | D22: José Pizarro | E22: 2 | G22: 46272 | H22: Hecho | I22: 46296 | J22: =IF($I22=J$14,"✔","") | K22: =IF($I22=K$14,"✔","") | L22: =IF($I22=L$14,"✔","") | M22: =IF($I22=M$14,"✔","") | N22: =IF($I22=N$14,"✔","") | O22: =IF($I22=O$14,"✔","") | P22: =IF($I22=P$14,"✔","") | Q22: =IF($I22=Q$14,"✔","") | ... AJ22: =IF($I22=AJ$14,"✔","") | AK22: A
A23: 9 | B23: Base de datos en la nube conectada con la página web | C23: Técnica | D23: José Pizarro | E23: 3 | G23: 46272 | H23: Hecho | I23: 46297 | J23: =IF($I23=J$14,"✔","") | K23: =IF($I23=K$14,"✔","") | L23: =IF($I23=L$14,"✔","") | M23: =IF($I23=M$14,"✔","") | N23: =IF($I23=N$14,"✔","") | O23: =IF($I23=O$14,"✔","") | P23: =IF($I23=P$14,"✔","") | Q23: =IF($I23=Q$14,"✔","") | ... AJ23: =IF($I23=AJ$14,"✔","") | AK23: A
A24: 10 | B24: Base de datos y API: fecha del remate y tipo extrajudicial | C24: Técnica | D24: José Pizarro | E24: 1 | G24: 46272 | H24: Hecho | I24: 46298 | J24: =IF($I24=J$14,"✔","") | K24: =IF($I24=K$14,"✔","") | L24: =IF($I24=L$14,"✔","") | M24: =IF($I24=M$14,"✔","") | N24: =IF($I24=N$14,"✔","") | O24: =IF($I24=O$14,"✔","") | P24: =IF($I24=P$14,"✔","") | Q24: =IF($I24=Q$14,"✔","") | ... AJ24: =IF($I24=AJ$14,"✔","") -> ✔ | AK24: A
A25: 11 | B25: Carga automática de remates (scrapeo de rematesinmobiliarios.cl), sin duplicados | C25: HU-10 | D25: José Pizarro | E25: 6 | G25: 46272 | H25: Hecho | I25: 46298 | J25: =IF($I25=J$14,"✔","") | K25: =IF($I25=K$14,"✔","") | L25: =IF($I25=L$14,"✔","") | M25: =IF($I25=M$14,"✔","") | N25: =IF($I25=N$14,"✔","") | O25: =IF($I25=O$14,"✔","") | P25: =IF($I25=P$14,"✔","") | Q25: =IF($I25=Q$14,"✔","") | ... AJ25: =IF($I25=AJ$14,"✔","") -> ✔ | AK25: A
A26: 12 | B26: Sprint Review de los sprints 2 y 4 | C26: Equipo | D26: José Pizarro | E26: 2 | G26: 46272 | H26: Hecho | I26: 46298 | J26: =IF($I26=J$14,"✔","") | K26: =IF($I26=K$14,"✔","") | L26: =IF($I26=L$14,"✔","") | M26: =IF($I26=M$14,"✔","") | N26: =IF($I26=N$14,"✔","") | O26: =IF($I26=O$14,"✔","") | P26: =IF($I26=P$14,"✔","") | Q26: =IF($I26=Q$14,"✔","") | ... AJ26: =IF($I26=AJ$14,"✔","") -> ✔ | AK26: A
B27: Total | E27: =SUM(E15:E26) -> 34 | F27: =SUM(F15:F26) -> 0 | H27: =COUNTIF(H15:H26,"Hecho")&" hechas" -> 12 hechas
A29: Burndown del sprint
A30: Día | B30: Fecha | C30: Ideal | D30: Pendientes
A31: 0 | B31: inicio | C31: =IF($C$10=0,"",ROUND($C$10-$C$10*A31/27,1)) -> 12 | D31: 12
A32: 1 | B32: 07-09 | C32: =IF($C$10=0,"",ROUND($C$10-$C$10*A32/27,1)) -> 11.6 | D32: 12
A33: 2 | B33: 08-09 | C33: =IF($C$10=0,"",ROUND($C$10-$C$10*A33/27,1)) -> 11.1 | D33: 12
A34: 3 | B34: 09-09 | C34: =IF($C$10=0,"",ROUND($C$10-$C$10*A34/27,1)) -> 10.7 | D34: 12
A35: 4 | B35: 10-09 | C35: =IF($C$10=0,"",ROUND($C$10-$C$10*A35/27,1)) -> 10.2 | D35: 12
A36: 5 | B36: 11-09 | C36: =IF($C$10=0,"",ROUND($C$10-$C$10*A36/27,1)) -> 9.8 | D36: 12
A37: 6 | B37: 12-09 | C37: =IF($C$10=0,"",ROUND($C$10-$C$10*A37/27,1)) -> 9.3 | D37: 12
A38: 7 | B38: 13-09 | C38: =IF($C$10=0,"",ROUND($C$10-$C$10*A38/27,1)) -> 8.9 | D38: 12
A39: 8 | B39: 14-09 | C39: =IF($C$10=0,"",ROUND($C$10-$C$10*A39/27,1)) -> 8.4 | D39: 10
A40: 9 | B40: 15-09 | C40: =IF($C$10=0,"",ROUND($C$10-$C$10*A40/27,1)) -> 8 | D40: 10
A41: 10 | B41: 16-09 | C41: =IF($C$10=0,"",ROUND($C$10-$C$10*A41/27,1)) -> 7.6 | D41: 10
A42: 11 | B42: 17-09 | C42: =IF($C$10=0,"",ROUND($C$10-$C$10*A42/27,1)) -> 7.1 | D42: 10
... A58: 27 | B58: 03-10 | C58: =IF($C$10=0,"",ROUND($C$10-$C$10*A58/27,1)) -> 0 | D58: 0

Sheet H13 Sprint 5
A1: Sprint 5 · Front-end web · 24-09 al 13-10-2026
B3: Sprint Goal | C3: Front-end web: pantallas del inversionista, el administrador y el analista
B4: Inicio | C4: 46289
B5: Término | C5: =IF(C4="","",C4+19) -> 46308
B6: Asistentes al Sprint Planning
B7: Historias comprometidas | C7: HU-02, HU-06, HU-07, HU-12, HU-15, HU-17 y HU-18
B8: Capacidad del sprint (h) | C8: =ROUND(2*10*20/7,0) -> 57
B9: Horas estimadas | C9: =SUM(E15:E28) -> 39
B10: Tareas comprometidas al inicio | C10: =COUNTIF(G15:G28,C4) -> 14
B11: Fecha de corte | C11: 46299
A13: Sprint Backlog | J13: Avance día a día (✔ = tarea terminada) | AD13: PO
A14: N.º | B14: Tarea | C14: Relación | D14: Responsable | E14: Horas est. | F14: Horas reales | G14: Alta | H14: Estado | I14: Término | J14: =IF($C$4="","",$C$4+0) -> 46289 | K14: =IF($C$4="","",$C$4+1) -> 46290 | L14: =IF($C$4="","",$C$4+2) -> 46291 | M14: =IF($C$4="","",$C$4+3) -> 46292 | N14: =IF($C$4="","",$C$4+4) -> 46293 | O14: =IF($C$4="","",$C$4+5) -> 46294 | P14: =IF($C$4="","",$C$4+6) -> 46295 | Q14: =IF($C$4="","",$C$4+7) -> 46296 | R14: =IF($C$4="","",$C$4+8) -> 46297 | S14: =IF($C$4="","",$C$4+9) -> 46298 | T14: =IF($C$4="","",$C$4+10) -> 46299 | U14: =IF($C$4="","",$C$4+11) -> 46300 | V14: =IF($C$4="","",$C$4+12) -> 46301 | W14: =IF($C$4="","",$C$4+13) -> 46302 | X14: =IF($C$4="","",$C$4+14) -> 46303 | Y14: =IF($C$4="","",$C$4+15) -> 46304 | Z14: =IF($C$4="","",$C$4+16) -> 46305 | AA14: =IF($C$4="","",$C$4+17) -> 46306 | AB14: =IF($C$4="","",$C$4+18) -> 46307 | AC14: =IF($C$4="","",$C$4+19) -> 46308 | AD14: PO (A/R)
A15: 1 | B15: Sesión en la web: login, token y /auth/me | C15: HU-01 | D15: José Pizarro | E15: 2 | G15: 46289 | H15: Hecho | I15: 46294 | J15: =IF($I15=J$14,"✔","") | K15: =IF($I15=K$14,"✔","") | L15: =IF($I15=L$14,"✔","") | M15: =IF($I15=M$14,"✔","") | N15: =IF($I15=N$14,"✔","") | O15: =IF($I15=O$14,"✔","") -> ✔ | P15: =IF($I15=P$14,"✔","") | Q15: =IF($I15=Q$14,"✔","") | ... AC15: =IF($I15=AC$14,"✔","") | AD15: A
A16: 2 | B16: Catálogo con filtros y detalle de propiedad en la web | C16: HU-02 · HU-06 · DEF-04 | D16: José Pizarro | E16: 3 | G16: 46289 | H16: Hecho | I16: 46294 | J16: =IF($I16=J$14,"✔","") | K16: =IF($I16=K$14,"✔","") | L16: =IF($I16=L$14,"✔","") | M16: =IF($I16=M$14,"✔","") | N16: =IF($I16=N$14,"✔","") | O16: =IF($I16=O$14,"✔","") -> ✔ | P16: =IF($I16=P$14,"✔","") | Q16: =IF($I16=Q$14,"✔","") | ... AC16: =IF($I16=AC$14,"✔","") | AD16: A
A17: 3 | B17: Guardados por API en la web (/favoritos) | C17: HU-07 | D17: José Pizarro | E17: 2 | G17: 46289 | H17: Hecho | I17: 46294 | J17: =IF($I17=J$14,"✔","") | K17: =IF($I17=K$14,"✔","") | L17: =IF($I17=L$14,"✔","") | M17: =IF($I17=M$14,"✔","") | N17: =IF($I17=N$14,"✔","") | O17: =IF($I17=O$14,"✔","") -> ✔ | P17: =IF($I17=P$14,"✔","") | Q17: =IF($I17=Q$14,"✔","") | ... AC17: =IF($I17=AC$14,"✔","") | AD17: A
A18: 4 | B18: Menú del administrador: Panel, Publicaciones, Opiniones y Anuncios | C18: HU-23 | D18: José Pizarro | E18: 2 | G18: 46289 | H18: Hecho | I18: 46294 | J18: =IF($I18=J$14,"✔","") | K18: =IF($I18=K$14,"✔","") | L18: =IF($I18=L$14,"✔","") | M18: =IF($I18=M$14,"✔","") | N18: =IF($I18=N$14,"✔","") | O18: =IF($I18=O$14,"✔","") -> ✔ | P18: =IF($I18=P$14,"✔","") | Q18: =IF($I18=Q$14,"✔","") | ... AC18: =IF($I18=AC$14,"✔","") | AD18: A
A19: 5 | B19: Opiniones: envío del inversionista y respuesta del administrador | C19: HU-18 | D19: José Pizarro | E19: 3 | G19: 46289 | H19: Hecho | I19: 46298 | J19: =IF($I19=J$14,"✔","") | K19: =IF($I19=K$14,"✔","") | L19: =IF($I19=L$14,"✔","") | M19: =IF($I19=M$14,"✔","") | N19: =IF($I19=N$14,"✔","") | O19: =IF($I19=O$14,"✔","") | P19: =IF($I19=P$14,"✔","") | Q19: =IF($I19=Q$14,"✔","") | ... AC19: =IF($I19=AC$14,"✔","") | AD19: A
A20: 6 | B20: Publicaciones del administrador con vistas y guardados | C20: HU-23 | D20: José Pizarro | E20: 2 | G20: 46289 | H20: Hecho | I20: 46295 | J20: =IF($I20=J$14,"✔","") | K20: =IF($I20=K$14,"✔","") | L20: =IF($I20=L$14,"✔","") | M20: =IF($I20=M$14,"✔","") | N20: =IF($I20=N$14,"✔","") | O20: =IF($I20=O$14,"✔","") | P20: =IF($I20=P$14,"✔","") -> ✔ | Q20: =IF($I20=Q$14,"✔","") | ... AC20: =IF($I20=AC$14,"✔","") | AD20: A
A21: 7 | B21: Catálogo: ordenar por fecha de remate (más próximo primero) | C21: HU-06 | D21: José Pizarro | E21: 1 | G21: 46289 | H21: Hecho | I21: 46298 | J21: =IF($I21=J$14,"✔","") | K21: =IF($I21=K$14,"✔","") | L21: =IF($I21=L$14,"✔","") | M21: =IF($I21=M$14,"✔","") | N21: =IF($I21=N$14,"✔","") | O21: =IF($I21=O$14,"✔","") | P21: =IF($I21=P$14,"✔","") | Q21: =IF($I21=Q$14,"✔","") | ... AC21: =IF($I21=AC$14,"✔","") | AD21: A
A22: 8 | B22: Panel del administrador: resumen de los últimos 7 días | C22: Entregable 15 | D22: José Pizarro | E22: 3 | G22: 46289 | H22: Hecho | I22: 46297 | J22: =IF($I22=J$14,"✔","") | K22: =IF($I22=K$14,"✔","") | L22: =IF($I22=L$14,"✔","") | M22: =IF($I22=M$14,"✔","") | N22: =IF($I22=N$14,"✔","") | O22: =IF($I22=O$14,"✔","") | P22: =IF($I22=P$14,"✔","") | Q22: =IF($I22=Q$14,"✔","") | ... AC22: =IF($I22=AC$14,"✔","") | AD22: A
A23: 9 | B23: Anuncios del administrador y notificaciones del inversionista | C23: HU-18 · HU-14 | D23: José Pizarro | E23: 4 | G23: 46289 | H23: Hecho | I23: 46297 | J23: =IF($I23=J$14,"✔","") | K23: =IF($I23=K$14,"✔","") | L23: =IF($I23=L$14,"✔","") | M23: =IF($I23=M$14,"✔","") | N23: =IF($I23=N$14,"✔","") | O23: =IF($I23=O$14,"✔","") | P23: =IF($I23=P$14,"✔","") | Q23: =IF($I23=Q$14,"✔","") | ... AC23: =IF($I23=AC$14,"✔","") | AD23: A
A24: 10 | B24: Perfil del inversionista y cambio de contraseña | C24: HU-12 | D24: José Pizarro | E24: 3 | G24: 46289 | H24: Hecho | I24: 46298 | J24: =IF($I24=J$14,"✔","") | K24: =IF($I24=K$14,"✔","") | L24: =IF($I24=L$14,"✔","") | M24: =IF($I24=M$14,"✔","") | N24: =IF($I24=N$14,"✔","") | O24: =IF($I24=O$14,"✔","") | P24: =IF($I24=P$14,"✔","") | Q24: =IF($I24=Q$14,"✔","") | ... AC24: =IF($I24=AC$14,"✔","") | AD24: A
A25: 11 | B25: Mapa de remates por comuna | C25: HU-15 | D25: Basthian Bascuñan | E25: 5 | G25: 46289 | H25: Hecho | J25: =IF($I25=J$14,"✔","") | K25: =IF($I25=K$14,"✔","") | L25: =IF($I25=L$14,"✔","") | M25: =IF($I25=M$14,"✔","") | N25: =IF($I25=N$14,"✔","") | O25: =IF($I25=O$14,"✔","") | P25: =IF($I25=P$14,"✔","") | Q25: =IF($I25=Q$14,"✔","") | ... AC25: =IF($I25=AC$14,"✔","")
A26: 12 | B26: Panel del analista: resumen, subastas, usuarios y alcance | C26: HU-17 | D26: Basthian Bascuñan | E26: 6 | G26: 46289 | H26: Por hacer | J26: =IF($I26=J$14,"✔","") | K26: =IF($I26=K$14,"✔","") | L26: =IF($I26=L$14,"✔","") | M26: =IF($I26=M$14,"✔","") | N26: =IF($I26=N$14,"✔","") | O26: =IF($I26=O$14,"✔","") | P26: =IF($I26=P$14,"✔","") | Q26: =IF($I26=Q$14,"✔","") | ... AC26: =IF($I26=AC$14,"✔","")
A27: 13 | B27: Encabezado de la web en celular | C27: DEF-07 | D27: José Pizarro | E27: 1 | G27: 46289 | H27: Por hacer | J27: =IF($I27=J$14,"✔","") | K27: =IF($I27=K$14,"✔","") | L27: =IF($I27=L$14,"✔","") | M27: =IF($I27=M$14,"✔","") | N27: =IF($I27=N$14,"✔","") | O27: =IF($I27=O$14,"✔","") | P27: =IF($I27=P$14,"✔","") | Q27: =IF($I27=Q$14,"✔","") | ... AC27: =IF($I27=AC$14,"✔","")
A28: 14 | B28: Sprint Review | C28: Equipo | D28: José Pizarro | E28: 2 | G28: 46289 | H28: Hecho | J28: =IF($I28=J$14,"✔","") | K28: =IF($I28=K$14,"✔","") | L28: =IF($I28=L$14,"✔","") | M28: =IF($I28=M$14,"✔","") | N28: =IF($I28=N$14,"✔","") | O28: =IF($I28=O$14,"✔","") | P28: =IF($I28=P$14,"✔","") | Q28: =IF($I28=Q$14,"✔","") | ... AC28: =IF($I28=AC$14,"✔","") | AD28: A
B29: Total | E29: =SUM(E15:E28) -> 39 | F29: =SUM(F15:F28) -> 0 | H29: =COUNTIF(H15:H28,"Hecho")&" hechas" -> 12 hechas
A31: Burndown del sprint
A32: Día | B32: Fecha | C32: Ideal | D32: Pendientes
A33: 0 | B33: inicio | C33: =IF($C$10=0,"",ROUND($C$10-$C$10*A33/20,1)) -> 14 | D33: 14
A34: 1 | B34: 24-09 | C34: =IF($C$10=0,"",ROUND($C$10-$C$10*A34/20,1)) -> 13.3 | D34: 14
A35: 2 | B35: 25-09 | C35: =IF($C$10=0,"",ROUND($C$10-$C$10*A35/20,1)) -> 12.6 | D35: 14
A36: 3 | B36: 26-09 | C36: =IF($C$10=0,"",ROUND($C$10-$C$10*A36/20,1)) -> 11.9 | D36: 14
A37: 4 | B37: 27-09 | C37: =IF($C$10=0,"",ROUND($C$10-$C$10*A37/20,1)) -> 11.2 | D37: 14
A38: 5 | B38: 28-09 | C38: =IF($C$10=0,"",ROUND($C$10-$C$10*A38/20,1)) -> 10.5 | D38: 14
A39: 6 | B39: 29-09 | C39: =IF($C$10=0,"",ROUND($C$10-$C$10*A39/20,1)) -> 9.8 | D39: 10
A40: 7 | B40: 30-09 | C40: =IF($C$10=0,"",ROUND($C$10-$C$10*A40/20,1)) -> 9.1 | D40: 9
A41: 8 | B41: 01-10 | C41: =IF($C$10=0,"",ROUND($C$10-$C$10*A41/20,1)) -> 8.4 | D41: 9
A42: 9 | B42: 02-10 | C42: =IF($C$10=0,"",ROUND($C$10-$C$10*A42/20,1)) -> 7.7 | D42: 9
A43: 10 | B43: 03-10 | C43: =IF($C$10=0,"",ROUND($C$10-$C$10*A43/20,1)) -> 7 | D43: 7
A44: 11 | B44: 04-10 | C44: =IF($C$10=0,"",ROUND($C$10-$C$10*A44/20,1)) -> 6.3 | D44: 7
A45: 12 | B45: 05-10 | C45: =IF($C$10=0,"",ROUND($C$10-$C$10*A45/20,1)) -> 5.6
A46: 13 | B46: 06-10 | C46: =IF($C$10=0,"",ROUND($C$10-$C$10*A46/20,1)) -> 4.9
A47: 14 | B47: 07-10 | C47: =IF($C$10=0,"",ROUND($C$10-$C$10*A47/20,1)) -> 4.2
A48: 15 | B48: 08-10 | C48: =IF($C$10=0,"",ROUND($C$10-$C$10*A48/20,1)) -> 3.5
A49: 16 | B49: 09-10 | C49: =IF($C$10=0,"",ROUND($C$10-$C$10*A49/20,1)) -> 2.8
A50: 17 | B50: 10-10 | C50: =IF($C$10=0,"",ROUND($C$10-$C$10*A50/20,1)) -> 2.1
A51: 18 | B51: 11-10 | C51: =IF($C$10=0,"",ROUND($C$10-$C$10*A51/20,1)) -> 1.4
A52: 19 | B52: 12-10 | C52: =IF($C$10=0,"",ROUND($C$10-$C$10*A52/20,1)) -> 0.7
A53: 20 | B53: 13-10 | C53: =IF($C$10=0,"",ROUND($C$10-$C$10*A53/20,1)) -> 0

Sheet H14 Sprint 6
A1: Sprint 6 · Conexión · 04-10 al 24-10-2026
A2: Ciclo: Conexión · 21 días · trabajan: Basthian Bascuñan y José Pizarro · plan del 04-10-2026 (un ciclo por sprint; los sprints se cruzan en fechas)
B3: Sprint Goal | C3: Conexión: conectar la app móvil (Android Studio) y la web con la API, y dejar la demostración en la nube
B4: Inicio | C4: 46299
B5: Término | C5: =IF(C4="","",C4+20) -> 46319
B6: Asistentes al Sprint Planning
B7: Historias comprometidas | C7: HU-04, HU-13, HU-14, HU-16, HU-19 y HU-20
B8: Capacidad del sprint (h) | C8: =ROUND(2*10*21/7,0) -> 60
B9: Horas estimadas | C9: =SUM(E15:E23) -> 36
B10: Tareas comprometidas al inicio | C10: =COUNTIF(G15:G23,C4) -> 9
B11: Fecha de corte | C11: 46299
A13: Sprint Backlog | J13: Avance día a día (✔ = tarea terminada) | AE13: PO
A14: N.º | B14: Tarea | C14: Relación | D14: Responsable | E14: Horas est. | F14: Horas reales | G14: Alta | H14: Estado | I14: Término | J14: =IF($C$4="","",$C$4+0) -> 46299 | K14: =IF($C$4="","",$C$4+1) -> 46300 | L14: =IF($C$4="","",$C$4+2) -> 46301 | M14: =IF($C$4="","",$C$4+3) -> 46302 | N14: =IF($C$4="","",$C$4+4) -> 46303 | O14: =IF($C$4="","",$C$4+5) -> 46304 | P14: =IF($C$4="","",$C$4+6) -> 46305 | Q14: =IF($C$4="","",$C$4+7) -> 46306 | R14: =IF($C$4="","",$C$4+8) -> 46307 | S14: =IF($C$4="","",$C$4+9) -> 46308 | T14: =IF($C$4="","",$C$4+10) -> 46309 | U14: =IF($C$4="","",$C$4+11) -> 46310 | V14: =IF($C$4="","",$C$4+12) -> 46311 | W14: =IF($C$4="","",$C$4+13) -> 46312 | X14: =IF($C$4="","",$C$4+14) -> 46313 | Y14: =IF($C$4="","",$C$4+15) -> 46314 | Z14: =IF($C$4="","",$C$4+16) -> 46315 | AA14: =IF($C$4="","",$C$4+17) -> 46316 | AB14: =IF($C$4="","",$C$4+18) -> 46317 | AC14: =IF($C$4="","",$C$4+19) -> 46318 | AD14: =IF($C$4="","",$C$4+20) -> 46319 | AE14: PO (A/R)
A15: 1 | B15: Corrección de DEF-03: crear la propiedad en una sola transacción | C15: HU-03 | D15: José Pizarro | E15: 1 | G15: 46299 | H15: Hecho | I15: 46299 | J15: =IF($I15=J$14,"✔","") -> ✔ | K15: =IF($I15=K$14,"✔","") | L15: =IF($I15=L$14,"✔","") | M15: =IF($I15=M$14,"✔","") | N15: =IF($I15=N$14,"✔","") | O15: =IF($I15=O$14,"✔","") | P15: =IF($I15=P$14,"✔","") | Q15: =IF($I15=Q$14,"✔","") | ... AD15: =IF($I15=AD$14,"✔","")
A16: 2 | B16: App: abrir el proyecto en Android Studio y conectarlo con la API (emulador y celular) | C16: HU-16 · HU-04 | D16: Basthian Bascuñan | E16: 5 | G16: 46299 | H16: Por hacer | J16: =IF($I16=J$14,"✔","") | K16: =IF($I16=K$14,"✔","") | L16: =IF($I16=L$14,"✔","") | M16: =IF($I16=M$14,"✔","") | N16: =IF($I16=N$14,"✔","") | O16: =IF($I16=O$14,"✔","") | P16: =IF($I16=P$14,"✔","") | Q16: =IF($I16=Q$14,"✔","") | ... AD16: =IF($I16=AD$14,"✔","")
A17: 3 | B17: App: registro e inicio de sesión contra la API (token) | C17: HU-16 · HU-01 | D17: Basthian Bascuñan | E17: 4 | G17: 46299 | H17: Hecho | I17: 46299 | J17: =IF($I17=J$14,"✔","") -> ✔ | K17: =IF($I17=K$14,"✔","") | L17: =IF($I17=L$14,"✔","") | M17: =IF($I17=M$14,"✔","") | N17: =IF($I17=N$14,"✔","") | O17: =IF($I17=O$14,"✔","") | P17: =IF($I17=P$14,"✔","") | Q17: =IF($I17=Q$14,"✔","") | ... AD17: =IF($I17=AD$14,"✔","")
A18: 4 | B18: App: catálogo y detalle con los datos de la API | C18: HU-16 · HU-02 | D18: Basthian Bascuñan | E18: 5 | G18: 46299 | H18: Hecho | I18: 46299 | J18: =IF($I18=J$14,"✔","") -> ✔ | K18: =IF($I18=K$14,"✔","") | L18: =IF($I18=L$14,"✔","") | M18: =IF($I18=M$14,"✔","") | N18: =IF($I18=N$14,"✔","") | O18: =IF($I18=O$14,"✔","") | P18: =IF($I18=P$14,"✔","") | Q18: =IF($I18=Q$14,"✔","") | ... AD18: =IF($I18=AD$14,"✔","")
A19: 5 | B19: App: guardados y notificaciones desde la API | C19: HU-16 · HU-07 | D19: Basthian Bascuñan | E19: 5 | G19: 46299 | H19: Por hacer | J19: =IF($I19=J$14,"✔","") | K19: =IF($I19=K$14,"✔","") | L19: =IF($I19=L$14,"✔","") | M19: =IF($I19=M$14,"✔","") | N19: =IF($I19=N$14,"✔","") | O19: =IF($I19=O$14,"✔","") | P19: =IF($I19=P$14,"✔","") | Q19: =IF($I19=Q$14,"✔","") | ... AD19: =IF($I19=AD$14,"✔","")
A20: 6 | B20: Web: alertas desde la API (reemplaza los datos de prueba del navegador) | C20: HU-13 | D20: José Pizarro | E20: 4 | G20: 46299 | H20: Por hacer | J20: =IF($I20=J$14,"✔","") | K20: =IF($I20=K$14,"✔","") | L20: =IF($I20=L$14,"✔","") | M20: =IF($I20=M$14,"✔","") | N20: =IF($I20=N$14,"✔","") | O20: =IF($I20=O$14,"✔","") | P20: =IF($I20=P$14,"✔","") | Q20: =IF($I20=Q$14,"✔","") | ... AD20: =IF($I20=AD$14,"✔","")
A21: 7 | B21: Despliegue de demostración (API, base de datos y web) | C21: HU-20 | D21: José Pizarro | E21: 5 | G21: 46299 | H21: Hecho | I21: 46299 | J21: =IF($I21=J$14,"✔","") -> ✔ | K21: =IF($I21=K$14,"✔","") | L21: =IF($I21=L$14,"✔","") | M21: =IF($I21=M$14,"✔","") | N21: =IF($I21=N$14,"✔","") | O21: =IF($I21=O$14,"✔","") | P21: =IF($I21=P$14,"✔","") | Q21: =IF($I21=Q$14,"✔","") | ... AD21: =IF($I21=AD$14,"✔","")
A22: 8 | B22: Pruebas de integración: registro, login, catálogo y semáforo (pytest + httpx) | C22: HU-19 | D22: José Pizarro | E22: 5 | G22: 46299 | H22: Hecho | I22: 46299 | J22: =IF($I22=J$14,"✔","") -> ✔ | K22: =IF($I22=K$14,"✔","") | L22: =IF($I22=L$14,"✔","") | M22: =IF($I22=M$14,"✔","") | N22: =IF($I22=N$14,"✔","") | O22: =IF($I22=O$14,"✔","") | P22: =IF($I22=P$14,"✔","") | Q22: =IF($I22=Q$14,"✔","") | ... AD22: =IF($I22=AD$14,"✔","")
A23: 9 | B23: Sprint Review | C23: Equipo | D23: José Pizarro | E23: 2 | G23: 46299 | H23: Por hacer | J23: =IF($I23=J$14,"✔","") | K23: =IF($I23=K$14,"✔","") | L23: =IF($I23=L$14,"✔","") | M23: =IF($I23=M$14,"✔","") | N23: =IF($I23=N$14,"✔","") | O23: =IF($I23=O$14,"✔","") | P23: =IF($I23=P$14,"✔","") | Q23: =IF($I23=Q$14,"✔","") | ... AD23: =IF($I23=AD$14,"✔","")
B24: Total | E24: =SUM(E15:E23) -> 36 | F24: =SUM(F15:F23) -> 0 | H24: =COUNTIF(H15:H23,"Hecho")&" hechas" -> 5 hechas
A26: Burndown del sprint
A27: Día | B27: Fecha | C27: Ideal | D27: Pendientes
A28: 0 | B28: inicio | C28: =IF($C$10=0,"",ROUND($C$10-$C$10*A28/21,1)) -> 9 | D28: 9
A29: 1 | B29: 04-10 | C29: =IF($C$10=0,"",ROUND($C$10-$C$10*A29/21,1)) -> 8.6 | D29: 8
A30: 2 | B30: 05-10 | C30: =IF($C$10=0,"",ROUND($C$10-$C$10*A30/21,1)) -> 8.1
A31: 3 | B31: 06-10 | C31: =IF($C$10=0,"",ROUND($C$10-$C$10*A31/21,1)) -> 7.7
A32: 4 | B32: 07-10 | C32: =IF($C$10=0,"",ROUND($C$10-$C$10*A32/21,1)) -> 7.3
A33: 5 | B33: 08-10 | C33: =IF($C$10=0,"",ROUND($C$10-$C$10*A33/21,1)) -> 6.9
A34: 6 | B34: 09-10 | C34: =IF($C$10=0,"",ROUND($C$10-$C$10*A34/21,1)) -> 6.4
A35: 7 | B35: 10-10 | C35: =IF($C$10=0,"",ROUND($C$10-$C$10*A35/21,1)) -> 6
A36: 8 | B36: 11-10 | C36: =IF($C$10=0,"",ROUND($C$10-$C$10*A36/21,1)) -> 5.6
A37: 9 | B37: 12-10 | C37: =IF($C$10=0,"",ROUND($C$10-$C$10*A37/21,1)) -> 5.1
A38: 10 | B38: 13-10 | C38: =IF($C$10=0,"",ROUND($C$10-$C$10*A38/21,1)) -> 4.7
A39: 11 | B39: 14-10 | C39: =IF($C$10=0,"",ROUND($C$10-$C$10*A39/21,1)) -> 4.3
A40: 12 | B40: 15-10 | C40: =IF($C$10=0,"",ROUND($C$10-$C$10*A40/21,1)) -> 3.9
A41: 13 | B41: 16-10 | C41: =IF($C$10=0,"",ROUND($C$10-$C$10*A41/21,1)) -> 3.4
... A49: 21 | B49: 24-10 | C49: =IF($C$10=0,"",ROUND($C$10-$C$10*A49/21,1)) -> 0

Sheet H15 Sprint 7
A1: Sprint 7 · Documentación fase 2 y cierre · 25-10 al 04-11-2026
B3: Sprint Goal | C3: Documentación fase 2 y cierre: pruebas, informe final y demostración
B4: Inicio | C4: 46300
B5: Término | C5: =IF(C4="","",C4+20) -> 46320
B6: Asistentes al Sprint Planning
B7: Historias comprometidas | C7: HU-19 y HU-21; cierre de la documentación
B8: Capacidad del sprint (h) | C8: =ROUND(3*10*11/7,0) -> 47
B9: Horas estimadas | C9: =SUM(E15:E22) -> 37
B10: Tareas comprometidas al inicio | C10: =COUNTIF(G15:G22,C4) -> 0
B11: Fecha de corte
A13: Sprint Backlog | J13: Avance día a día (✔ = tarea terminada) | U13: PO
A14: N.º | B14: Tarea | C14: Relación | D14: Responsable | E14: Horas est. | F14: Horas reales | G14: Alta | H14: Estado | I14: Término | J14: =IF($C$4="","",$C$4+0) -> 46300 | K14: =IF($C$4="","",$C$4+1) -> 46301 | L14: =IF($C$4="","",$C$4+2) -> 46302 | M14: =IF($C$4="","",$C$4+3) -> 46303 | N14: =IF($C$4="","",$C$4+4) -> 46304 | O14: =IF($C$4="","",$C$4+5) -> 46305 | P14: =IF($C$4="","",$C$4+6) -> 46306 | Q14: =IF($C$4="","",$C$4+7) -> 46307 | R14: =IF($C$4="","",$C$4+8) -> 46308 | S14: =IF($C$4="","",$C$4+9) -> 46309 | T14: =IF($C$4="","",$C$4+10) -> 46310 | U14: PO (A/R)
A15: 1 | B15: Actualizar el informe: fuente de datos, calendario de sprints y reglas nuevas del semáforo | C15: Documentación | D15: Matías Negrete | E15: 5 | G15: 46320 | H15: Por hacer | J15: =IF($I15=J$14,"✔","") | K15: =IF($I15=K$14,"✔","") | L15: =IF($I15=L$14,"✔","") | M15: =IF($I15=M$14,"✔","") | N15: =IF($I15=N$14,"✔","") | O15: =IF($I15=O$14,"✔","") | P15: =IF($I15=P$14,"✔","") | Q15: =IF($I15=Q$14,"✔","") | ... T15: =IF($I15=T$14,"✔","")
A16: 2 | B16: Guía del estudiante 2.4 e Informe final 2.6 del Proyecto APT | C16: Documentación | D16: Matías Negrete | E16: 5 | G16: 46302 | H16: Hecho | I16: 46302 | J16: =IF($I16=J$14,"✔","") | K16: =IF($I16=K$14,"✔","") | L16: =IF($I16=L$14,"✔","") -> ✔ | M16: =IF($I16=M$14,"✔","") | N16: =IF($I16=N$14,"✔","") | O16: =IF($I16=O$14,"✔","") | P16: =IF($I16=P$14,"✔","") | Q16: =IF($I16=Q$14,"✔","") | ... T16: =IF($I16=T$14,"✔","")
A17: 3 | B17: Presentación final y demostración | C17: Documentación | D17: Matías Negrete | E17: 4 | G17: 46320 | H17: Por hacer | J17: =IF($I17=J$14,"✔","") | K17: =IF($I17=K$14,"✔","") | L17: =IF($I17=L$14,"✔","") | M17: =IF($I17=M$14,"✔","") | N17: =IF($I17=N$14,"✔","") | O17: =IF($I17=O$14,"✔","") | P17: =IF($I17=P$14,"✔","") | Q17: =IF($I17=Q$14,"✔","") | ... T17: =IF($I17=T$14,"✔","")
A18: 4 | B18: Ejecutar los casos de prueba pendientes, las re-pruebas y el informe de pruebas | C18: HU-19 | D18: José Pizarro | E18: 6 | G18: 46320 | H18: Por hacer | J18: =IF($I18=J$14,"✔","") | K18: =IF($I18=K$14,"✔","") | L18: =IF($I18=L$14,"✔","") | M18: =IF($I18=M$14,"✔","") | N18: =IF($I18=N$14,"✔","") | O18: =IF($I18=O$14,"✔","") | P18: =IF($I18=P$14,"✔","") | Q18: =IF($I18=Q$14,"✔","") | ... T18: =IF($I18=T$14,"✔","")
A19: 5 | B19: Pruebas de la app en el celular y en el emulador | C19: HU-16 · HU-19 | D19: Basthian Bascuñan | E19: 4 | G19: 46320 | H19: Por hacer | J19: =IF($I19=J$14,"✔","") | K19: =IF($I19=K$14,"✔","") | L19: =IF($I19=L$14,"✔","") | M19: =IF($I19=M$14,"✔","") | N19: =IF($I19=N$14,"✔","") | O19: =IF($I19=O$14,"✔","") | P19: =IF($I19=P$14,"✔","") | Q19: =IF($I19=Q$14,"✔","") | ... T19: =IF($I19=T$14,"✔","")
A20: 6 | B20: Corregir los defectos que aparezcan en las pruebas de la app | C20: Defectos | D20: Basthian Bascuñan | E20: 5 | G20: 46320 | H20: Por hacer | J20: =IF($I20=J$14,"✔","") | K20: =IF($I20=K$14,"✔","") | L20: =IF($I20=L$14,"✔","") | M20: =IF($I20=M$14,"✔","") | N20: =IF($I20=N$14,"✔","") | O20: =IF($I20=O$14,"✔","") | P20: =IF($I20=P$14,"✔","") | Q20: =IF($I20=Q$14,"✔","") | ... T20: =IF($I20=T$14,"✔","")
A21: 7 | B21: Validación con 5 usuarios (escala SUS) | C21: HU-21 | D21: Basthian Bascuñan | E21: 5 | G21: 46320 | H21: Por hacer | J21: =IF($I21=J$14,"✔","") | K21: =IF($I21=K$14,"✔","") | L21: =IF($I21=L$14,"✔","") | M21: =IF($I21=M$14,"✔","") | N21: =IF($I21=N$14,"✔","") | O21: =IF($I21=O$14,"✔","") | P21: =IF($I21=P$14,"✔","") | Q21: =IF($I21=Q$14,"✔","") | ... T21: =IF($I21=T$14,"✔","")
A22: 8 | B22: Sprint Review y retrospectiva final | C22: Equipo | D22: José Pizarro | E22: 3 | G22: 46320 | H22: Por hacer | J22: =IF($I22=J$14,"✔","") | K22: =IF($I22=K$14,"✔","") | L22: =IF($I22=L$14,"✔","") | M22: =IF($I22=M$14,"✔","") | N22: =IF($I22=N$14,"✔","") | O22: =IF($I22=O$14,"✔","") | P22: =IF($I22=P$14,"✔","") | Q22: =IF($I22=Q$14,"✔","") | ... T22: =IF($I22=T$14,"✔","")
B23: Total | E23: =SUM(E15:E22) -> 37 | F23: =SUM(F15:F22) -> 0 | H23: =COUNTIF(H15:H22,"Hecho")&" hechas" -> 1 hechas
A25: Burndown del sprint
A26: Día | B26: Fecha | C26: Ideal | D26: Pendientes
A27: 0 | B27: inicio | C27: =IF($C$10=0,"",ROUND($C$10-$C$10*A27/11,1)) | D27: 8
A28: 1 | B28: 25-10 | C28: =IF($C$10=0,"",ROUND($C$10-$C$10*A28/11,1))
A29: 2 | B29: 26-10 | C29: =IF($C$10=0,"",ROUND($C$10-$C$10*A29/11,1))
A30: 3 | B30: 27-10 | C30: =IF($C$10=0,"",ROUND($C$10-$C$10*A30/11,1))
A31: 4 | B31: 28-10 | C31: =IF($C$10=0,"",ROUND($C$10-$C$10*A31/11,1))
A32: 5 | B32: 29-10 | C32: =IF($C$10=0,"",ROUND($C$10-$C$10*A32/11,1))
A33: 6 | B33: 30-10 | C33: =IF($C$10=0,"",ROUND($C$10-$C$10*A33/11,1))
A34: 7 | B34: 31-10 | C34: =IF($C$10=0,"",ROUND($C$10-$C$10*A34/11,1))
A35: 8 | B35: 01-11 | C35: =IF($C$10=0,"",ROUND($C$10-$C$10*A35/11,1))
A36: 9 | B36: 02-11 | C36: =IF($C$10=0,"",ROUND($C$10-$C$10*A36/11,1))
A37: 10 | B37: 03-11 | C37: =IF($C$10=0,"",ROUND($C$10-$C$10*A37/11,1))
A38: 11 | B38: 04-11 | C38: =IF($C$10=0,"",ROUND($C$10-$C$10*A38/11,1))

Sheet I1 Plan de pruebas
A1: Plan de pruebas
A4: Elemento | B4: Definición
A5: Objetivo | B5: Comprobar que HouseGreen cumple los requisitos funcionales y no funcionales y que el semáforo clasifica sin errores lógicos.
A6: Alcance | B6: Motor de reglas, API REST, web, app, ingesta, seguridad y requisitos no funcionales (rendimiento, carga, concurrencia, latencia, disponibilidad, accesibilidad, usabilidad y geolocalización).
A7: Fuera de alcance | B7: Pagos en línea, integración con servicios de IA y datos de fuentes oficiales no disponibles para el MVP.
A8: Estrategia | B8: Pirámide de pruebas: muchas pruebas unitarias, algunas de integración y de API, y pocas de extremo a extremo. Las reglas del semáforo se prueban en los bordes de cada umbral y cada defecto corregido suma una prueba para que no vuelva.
A9: Tipos de prueba | B9: Unitarias, integración, API, reglas de negocio, funcionales, seguridad, rendimiento, carga, concurrencia, accesibilidad, usabilidad y geolocalización.
A10: Ambiente | B10: Base PostgreSQL de prueba creada con los scripts del proyecto (52 comunas y propiedades de prueba); ambiente de demostración en la nube para las pruebas no funcionales.
A11: Herramientas | B11: pytest + httpx (API), Playwright (web), Locust (rendimiento y carga), Lighthouse y axe (accesibilidad), OWASP ZAP (seguridad) y cuestionario SUS.
A12: Datos de prueba | B12: Propiedades del prototipo con resultado conocido: verde 8/10, amarilla 6/10, roja por veto y roja sin puntaje.
A13: Responsables | B13: José Pizarro coordina, registra y automatiza las pruebas de la web y la API; Basthian Bascuñan prueba la app y hace la validación con usuarios; Matías Negrete valida contra los criterios de aceptación.
A14: Calendario | B14: Pruebas de cada historia dentro de su sprint; pruebas de integración en el Sprint 6; pruebas no funcionales, de la app y de usabilidad con usuarios en el Sprint 7.
A15: Criterios de entrada | B15: La historia cumple la parte de desarrollo de la Definition of Done, el código compila y los datos de prueba están cargados.
... A18: Gestión de defectos | B18: Cada fallo se registra con severidad, corrección, re-prueba y estado en el registro de defectos.

Sheet I2 Casos de prueba
A1: Casos de prueba
A4: ID | B4: Requisito | C4: HU | D4: Tipo | E4: Crítico | F4: Caso | G4: Resultado esperado | H4: Resultado obtenido | I4: Fecha | J4: Ambiente | K4: Estado | L4: Defecto | M4: Sprint
A5: CP-01 | B5: RF-01 | C5: HU-01 | D5: Funcional | E5: Sí | F5: Registro con correo y contraseña válidos | G5: Cuenta creada con rol inversionista; contraseña guardada como hash bcrypt | K5: Pendiente | M5: 4
A6: CP-02 | B6: RF-01 | C6: HU-01 | D6: Funcional | E6: No | F6: Registro con un correo ya usado | G6: Rechazo con mensaje claro; no se crea otra cuenta | K6: Pendiente | M6: 4
A7: CP-03 | B7: RF-01 | C7: HU-01 | D7: Seguridad | E7: Sí | F7: Inicio de sesión con contraseña incorrecta | G7: Respuesta 401 sin indicar si el correo existe | K7: Pendiente | M7: 4
A8: CP-04 | B8: RF-02 | C8: HU-09 | D8: Seguridad | E8: Sí | F8: El administrador ingresa un código TOTP vencido o ya usado | G8: Acceso denegado y el intento queda en la auditoría | K8: Pendiente | M8: —
A9: CP-05 | B9: Entreg. 17 | C9: HU-22 | D9: Seguridad | E9: Sí | F9: Un inversionista intenta crear o editar una propiedad | G9: Respuesta 403 | K9: Pendiente | M9: —
A10: CP-06 | B10: RF-15 | C10: HU-17 | D10: Seguridad | E10: No | F10: El analista intenta una operación de escritura | G10: Respuesta 403 | K10: Pendiente | M10: 5
A11: CP-07 | B11: RF-08 | C11: HU-03 | D11: Regla de negocio | E11: Sí | F11: Propiedad del ejemplo: descuento 42,3 %, deuda 1,5 %, 1 acreedor, 1,5 meses, comuna roja | G11: 8/10, zona verde, sin veto | H11: 8/10, zona verde, sin veto; oferta máxima $51.700.000 | I11: 30-09 | J11: Modelo de referencia (SQL) | K11: Aprobado | M11: 4
A12: CP-08 | B12: RF-08 | C12: HU-03 | D12: Regla de negocio | E12: Sí | F12: Estado legal con 1, 2, 3 y 4 gravámenes | G12: 2, 1, 1 y 0 puntos | H12: 2, 1, 1 y 0 puntos, tras corregir DEF-06 | I12: 28-09 | J12: Base del proyecto | K12: Aprobado | L12: DEF-06 | M12: 4
A13: CP-09 | B13: RF-08 | C13: HU-03 | D13: Regla de negocio | E13: Sí | F13: Propiedad sin comparables de mercado | G13: Zona roja sin puntaje (regla de completitud) | H13: Las 3 propiedades de prueba sin comparables quedaron en zona roja sin puntaje | I13: 28-09 | J13: Base del proyecto | K13: Aprobado | M13: 4
A14: CP-10 | B14: RF-08 | C14: HU-03 | D14: Regla de negocio | E14: Sí | F14: Propiedad con usufructo vitalicio y buen puntaje | G14: Zona roja por veto, con el motivo guardado | H14: Puntaje 6, zona roja por veto, motivo «Usufructo vitalicio» | I14: 30-09 | J14: Modelo de referencia (SQL) | K14: Aprobado | M14: 4
A15: CP-11 | B15: RF-08 | C15: HU-03 | D15: Regla de negocio | E15: Sí | F15: Descuento real de 14,9 %, 15 %, 39,9 % y 40 % | G15: Factor 1: roja con veto, amarilla, amarilla y verde | H15: Roja con veto «Descuento real menor a 15 %», amarilla, amarilla y verde | I15: 30-09 | J15: Modelo de referencia (SQL) | K15: Aprobado | M15: 4
A16: CP-12 | B16: RF-08 | C16: HU-03 | D16: Integración | E16: Sí | F16: Guardar una propiedad nueva | G16: Se crea su evaluación | H16: 2 de las 3 propiedades «Casa test 2» quedaron sin evaluación | I16: 28-09 | J16: Base del proyecto | K16: Fallido | L16: DEF-01 | M16: 4
A17: CP-13 | B17: RF-04 | C17: HU-03 | D17: Integración | E17: No | F17: Editar una propiedad con comparables y deudas | G17: Se reemplazan los datos, sin duplicados | H17: 28-09: se duplicaban (DEF-02). 29-09: corrección aplicada; falta la re-prueba | I17: 29-09 | J17: Base del proyecto | K17: Pendiente | L17: DEF-02 | M17: 4
A18: CP-14 | B18: RF-09 | C18: HU-05 | D18: Funcional | E18: Sí | F18: Abrir el detalle de una propiedad en la web | G18: Semáforo con los 5 factores, sus puntos y su fuente | H18: 28-09: la vista no compilaba (DEF-04). 29-09: compila y muestra datos y evaluación; falta el detalle por factor | I18: 29-09 | J18: Base del proyecto | K18: Pendiente | L18: DEF-04 | M18: 4
A19: CP-15 | B19: RF-14 | C19: HU-08 | D19: Funcional | E19: No | F19: Guardar el formulario del administrador con un campo vacío | G19: El campo queda vacío (null), no en 0 | H19: Anulado el 29-09: el administrador ya no crea propiedades | I19: 29-09 | J19: Base del proyecto | K19: Anulado | L19: DEF-05 | M19: 4
A20: CP-16 | B20: RF-06 | C20: HU-06 | D20: Funcional | E20: No | F20: Filtrar por Maipú y precio hasta $80.000.000 | G20: Solo propiedades que cumplen ambos filtros, en menos de 2 s | K20: Pendiente | M20: 5
A21: CP-17 | B21: RF-07 | C21: HU-07 | D21: Seguridad | E21: Sí | F21: Pedir los guardados de otro usuario cambiando el id | G21: Respuesta 403 o 404, sin datos ajenos | K21: Pendiente | M21: 5
A22: CP-18 | B22: RF-11 | C22: HU-13 | D22: Funcional | E22: No | F22: La ingesta carga una propiedad que calza con un filtro guardado | G22: Alerta enviada en menos de 5 minutos | K22: Pendiente | M22: 6
A23: CP-19 | B23: RF-14 | C23: HU-10 | D23: Integración | E23: No | F23: La ingesta recibe un aviso sin rol de avalúo | G23: Se descarta, queda registrado y la carga sigue | K23: Pendiente | M23: 4
A24: CP-20 | B24: RF-14 | C24: HU-10 | D24: Integración | E24: Sí | F24: La ingesta lee dos veces el mismo aviso | G24: No se duplica la propiedad | H24: Se rechaza el duplicado por la restricción única; falta probar la ingesta | I24: 30-09 | J24: Modelo de referencia (SQL) | K24: Pendiente | M24: 4
A25: CP-21 | B25: RF-10 | C25: HU-11 | D25: Funcional | E25: No | F25: Cambiar el umbral verde del factor 1 | G25: Nueva versión de reglas y recálculo de las publicaciones activas | K25: Pendiente | M25: —
A26: CP-22 | B26: RF-07 | C26: HU-07 | D26: Funcional | E26: No | F26: Guardar y quitar una propiedad desde la web | G26: Se registra en la base y se mantiene al volver a entrar | H26: La web usa GET, POST y DELETE /favoritos; verificado en la base | I26: 29-09 | J26: Base del proyecto | K26: Aprobado | M26: 5
A27: CP-23 | B27: RF-15 | C27: HU-23 | D27: Funcional | E27: No | F27: Un inversionista abre el detalle de una propiedad | G27: Se registra una vista (una por persona cada 30 minutos; solo inversionistas) | H27: POST /propiedades/{id}/vista verificado en /docs y en la base | I27: 29-09 | J27: Base del proyecto | K27: Aprobado | M27: 4
A28: CP-24 | B28: Entreg. 5 | C28: HU-22 | D28: Seguridad | E28: Sí | F28: Un inversionista abre /admin en la web | G28: No ve el menú Admin y la ruta lo devuelve al inicio | H28: Implementado el 29-09 (ProtectedRoute soloAdmin); falta registrar la prueba | J28: Base del proyecto | K28: Pendiente | M28: —

Sheet I3 Pruebas funcionales
A1: Pruebas funcionales: resumen
A4: HU | B4: Funcionalidad | C4: Casos | D4: Aprobados | E4: Fallidos | F4: Pendientes | G4: Anulados | H4: % aprobado (ejecutados)
A5: HU-01 | B5: Registro e inicio de sesión | C5: =COUNTIF('I2 Casos de prueba'!$C$5:$C$28,A5) -> 3 | D5: =COUNTIFS('I2 Casos de prueba'!$C$5:$C$28,A5,'I2 Casos de prueba'!$K$5:$K$28,"Aprobado") -> 0 | E5: =COUNTIFS('I2 Casos de prueba'!$C$5:$C$28,A5,'I2 Casos de prueba'!$K$5:$K$28,"Fallido") -> 0 | F5: =COUNTIFS('I2 Casos de prueba'!$C$5:$C$28,A5,'I2 Casos de prueba'!$K$5:$K$28,"Pendiente") -> 3 | G5: =COUNTIFS('I2 Casos de prueba'!$C$5:$C$28,A5,'I2 Casos de prueba'!$K$5:$K$28,"Anulado") -> 0 | H5: =IF(D5+E5=0,"—",D5/(D5+E5)) -> —
A6: HU-03 | B6: Semáforo automático | C6: =COUNTIF('I2 Casos de prueba'!$C$5:$C$28,A6) -> 7 | D6: =COUNTIFS('I2 Casos de prueba'!$C$5:$C$28,A6,'I2 Casos de prueba'!$K$5:$K$28,"Aprobado") -> 5 | E6: =COUNTIFS('I2 Casos de prueba'!$C$5:$C$28,A6,'I2 Casos de prueba'!$K$5:$K$28,"Fallido") -> 1 | F6: =COUNTIFS('I2 Casos de prueba'!$C$5:$C$28,A6,'I2 Casos de prueba'!$K$5:$K$28,"Pendiente") -> 1 | G6: =COUNTIFS('I2 Casos de prueba'!$C$5:$C$28,A6,'I2 Casos de prueba'!$K$5:$K$28,"Anulado") -> 0 | H6: =IF(D6+E6=0,"—",D6/(D6+E6)) -> 0.83333333
A7: HU-05 | B7: Detalle por factor | C7: =COUNTIF('I2 Casos de prueba'!$C$5:$C$28,A7) -> 1 | D7: =COUNTIFS('I2 Casos de prueba'!$C$5:$C$28,A7,'I2 Casos de prueba'!$K$5:$K$28,"Aprobado") -> 0 | E7: =COUNTIFS('I2 Casos de prueba'!$C$5:$C$28,A7,'I2 Casos de prueba'!$K$5:$K$28,"Fallido") -> 0 | F7: =COUNTIFS('I2 Casos de prueba'!$C$5:$C$28,A7,'I2 Casos de prueba'!$K$5:$K$28,"Pendiente") -> 1 | G7: =COUNTIFS('I2 Casos de prueba'!$C$5:$C$28,A7,'I2 Casos de prueba'!$K$5:$K$28,"Anulado") -> 0 | H7: =IF(D7+E7=0,"—",D7/(D7+E7)) -> —
A8: HU-06 | B8: Filtros | C8: =COUNTIF('I2 Casos de prueba'!$C$5:$C$28,A8) -> 1 | D8: =COUNTIFS('I2 Casos de prueba'!$C$5:$C$28,A8,'I2 Casos de prueba'!$K$5:$K$28,"Aprobado") -> 0 | E8: =COUNTIFS('I2 Casos de prueba'!$C$5:$C$28,A8,'I2 Casos de prueba'!$K$5:$K$28,"Fallido") -> 0 | F8: =COUNTIFS('I2 Casos de prueba'!$C$5:$C$28,A8,'I2 Casos de prueba'!$K$5:$K$28,"Pendiente") -> 1 | G8: =COUNTIFS('I2 Casos de prueba'!$C$5:$C$28,A8,'I2 Casos de prueba'!$K$5:$K$28,"Anulado") -> 0 | H8: =IF(D8+E8=0,"—",D8/(D8+E8)) -> —
A9: HU-07 | B9: Guardados | C9: =COUNTIF('I2 Casos de prueba'!$C$5:$C$28,A9) -> 2 | D9: =COUNTIFS('I2 Casos de prueba'!$C$5:$C$28,A9,'I2 Casos de prueba'!$K$5:$K$28,"Aprobado") -> 1 | E9: =COUNTIFS('I2 Casos de prueba'!$C$5:$C$28,A9,'I2 Casos de prueba'!$K$5:$K$28,"Fallido") -> 0 | F9: =COUNTIFS('I2 Casos de prueba'!$C$5:$C$28,A9,'I2 Casos de prueba'!$K$5:$K$28,"Pendiente") -> 1 | G9: =COUNTIFS('I2 Casos de prueba'!$C$5:$C$28,A9,'I2 Casos de prueba'!$K$5:$K$28,"Anulado") -> 0 | H9: =IF(D9+E9=0,"—",D9/(D9+E9)) -> 1
A10: HU-08 | B10: Fotos y descripción | C10: =COUNTIF('I2 Casos de prueba'!$C$5:$C$28,A10) -> 1 | D10: =COUNTIFS('I2 Casos de prueba'!$C$5:$C$28,A10,'I2 Casos de prueba'!$K$5:$K$28,"Aprobado") -> 0 | E10: =COUNTIFS('I2 Casos de prueba'!$C$5:$C$28,A10,'I2 Casos de prueba'!$K$5:$K$28,"Fallido") -> 0 | F10: =COUNTIFS('I2 Casos de prueba'!$C$5:$C$28,A10,'I2 Casos de prueba'!$K$5:$K$28,"Pendiente") -> 0 | G10: =COUNTIFS('I2 Casos de prueba'!$C$5:$C$28,A10,'I2 Casos de prueba'!$K$5:$K$28,"Anulado") -> 1 | H10: =IF(D10+E10=0,"—",D10/(D10+E10)) -> —
A11: HU-09 | B11: 2FA del administrador | C11: =COUNTIF('I2 Casos de prueba'!$C$5:$C$28,A11) -> 1 | D11: =COUNTIFS('I2 Casos de prueba'!$C$5:$C$28,A11,'I2 Casos de prueba'!$K$5:$K$28,"Aprobado") -> 0 | E11: =COUNTIFS('I2 Casos de prueba'!$C$5:$C$28,A11,'I2 Casos de prueba'!$K$5:$K$28,"Fallido") -> 0 | F11: =COUNTIFS('I2 Casos de prueba'!$C$5:$C$28,A11,'I2 Casos de prueba'!$K$5:$K$28,"Pendiente") -> 1 | G11: =COUNTIFS('I2 Casos de prueba'!$C$5:$C$28,A11,'I2 Casos de prueba'!$K$5:$K$28,"Anulado") -> 0 | H11: =IF(D11+E11=0,"—",D11/(D11+E11)) -> —
A12: HU-10 | B12: Ingesta | C12: =COUNTIF('I2 Casos de prueba'!$C$5:$C$28,A12) -> 2 | D12: =COUNTIFS('I2 Casos de prueba'!$C$5:$C$28,A12,'I2 Casos de prueba'!$K$5:$K$28,"Aprobado") -> 0 | E12: =COUNTIFS('I2 Casos de prueba'!$C$5:$C$28,A12,'I2 Casos de prueba'!$K$5:$K$28,"Fallido") -> 0 | F12: =COUNTIFS('I2 Casos de prueba'!$C$5:$C$28,A12,'I2 Casos de prueba'!$K$5:$K$28,"Pendiente") -> 2 | G12: =COUNTIFS('I2 Casos de prueba'!$C$5:$C$28,A12,'I2 Casos de prueba'!$K$5:$K$28,"Anulado") -> 0 | H12: =IF(D12+E12=0,"—",D12/(D12+E12)) -> —
A13: HU-11 | B13: Reglas configurables | C13: =COUNTIF('I2 Casos de prueba'!$C$5:$C$28,A13) -> 1 | D13: =COUNTIFS('I2 Casos de prueba'!$C$5:$C$28,A13,'I2 Casos de prueba'!$K$5:$K$28,"Aprobado") -> 0 | E13: =COUNTIFS('I2 Casos de prueba'!$C$5:$C$28,A13,'I2 Casos de prueba'!$K$5:$K$28,"Fallido") -> 0 | F13: =COUNTIFS('I2 Casos de prueba'!$C$5:$C$28,A13,'I2 Casos de prueba'!$K$5:$K$28,"Pendiente") -> 1 | G13: =COUNTIFS('I2 Casos de prueba'!$C$5:$C$28,A13,'I2 Casos de prueba'!$K$5:$K$28,"Anulado") -> 0 | H13: =IF(D13+E13=0,"—",D13/(D13+E13)) -> —
A14: HU-13 | B14: Alertas | C14: =COUNTIF('I2 Casos de prueba'!$C$5:$C$28,A14) -> 1 | D14: =COUNTIFS('I2 Casos de prueba'!$C$5:$C$28,A14,'I2 Casos de prueba'!$K$5:$K$28,"Aprobado") -> 0 | E14: =COUNTIFS('I2 Casos de prueba'!$C$5:$C$28,A14,'I2 Casos de prueba'!$K$5:$K$28,"Fallido") -> 0 | F14: =COUNTIFS('I2 Casos de prueba'!$C$5:$C$28,A14,'I2 Casos de prueba'!$K$5:$K$28,"Pendiente") -> 1 | G14: =COUNTIFS('I2 Casos de prueba'!$C$5:$C$28,A14,'I2 Casos de prueba'!$K$5:$K$28,"Anulado") -> 0 | H14: =IF(D14+E14=0,"—",D14/(D14+E14)) -> —
A15: HU-17 | B15: Panel del analista | C15: =COUNTIF('I2 Casos de prueba'!$C$5:$C$28,A15) -> 1 | D15: =COUNTIFS('I2 Casos de prueba'!$C$5:$C$28,A15,'I2 Casos de prueba'!$K$5:$K$28,"Aprobado") -> 0 | E15: =COUNTIFS('I2 Casos de prueba'!$C$5:$C$28,A15,'I2 Casos de prueba'!$K$5:$K$28,"Fallido") -> 0 | F15: =COUNTIFS('I2 Casos de prueba'!$C$5:$C$28,A15,'I2 Casos de prueba'!$K$5:$K$28,"Pendiente") -> 1 | G15: =COUNTIFS('I2 Casos de prueba'!$C$5:$C$28,A15,'I2 Casos de prueba'!$K$5:$K$28,"Anulado") -> 0 | H15: =IF(D15+E15=0,"—",D15/(D15+E15)) -> —
A16: HU-22 | B16: Seguridad y roles | C16: =COUNTIF('I2 Casos de prueba'!$C$5:$C$28,A16) -> 2 | D16: =COUNTIFS('I2 Casos de prueba'!$C$5:$C$28,A16,'I2 Casos de prueba'!$K$5:$K$28,"Aprobado") -> 0 | E16: =COUNTIFS('I2 Casos de prueba'!$C$5:$C$28,A16,'I2 Casos de prueba'!$K$5:$K$28,"Fallido") -> 0 | F16: =COUNTIFS('I2 Casos de prueba'!$C$5:$C$28,A16,'I2 Casos de prueba'!$K$5:$K$28,"Pendiente") -> 2 | G16: =COUNTIFS('I2 Casos de prueba'!$C$5:$C$28,A16,'I2 Casos de prueba'!$K$5:$K$28,"Anulado") -> 0 | H16: =IF(D16+E16=0,"—",D16/(D16+E16)) -> —
A17: HU-23 | B17: Vistas por publicación | C17: =COUNTIF('I2 Casos de prueba'!$C$5:$C$28,A17) -> 1 | D17: =COUNTIFS('I2 Casos de prueba'!$C$5:$C$28,A17,'I2 Casos de prueba'!$K$5:$K$28,"Aprobado") -> 1 | E17: =COUNTIFS('I2 Casos de prueba'!$C$5:$C$28,A17,'I2 Casos de prueba'!$K$5:$K$28,"Fallido") -> 0 | F17: =COUNTIFS('I2 Casos de prueba'!$C$5:$C$28,A17,'I2 Casos de prueba'!$K$5:$K$28,"Pendiente") -> 0 | G17: =COUNTIFS('I2 Casos de prueba'!$C$5:$C$28,A17,'I2 Casos de prueba'!$K$5:$K$28,"Anulado") -> 0 | H17: =IF(D17+E17=0,"—",D17/(D17+E17)) -> 1
A18: Total | C18: =SUM(C5:C17) -> 24 | D18: =SUM(D5:D17) -> 7 | E18: =SUM(E5:E17) -> 1 | F18: =SUM(F5:F17) -> 15 | G18: =SUM(G5:G17) -> 1 | H18: =IF(D18+E18=0,"—",D18/(D18+E18)) -> 0.875
B20: Criterios de salida del plan de pruebas
B21: Criterio de salida | C21: Meta | D21: Al 30-09
B22: Casos críticos aprobados | C22: 1 | D22: =COUNTIFS('I2 Casos de prueba'!$E$5:$E$28,"Sí",'I2 Casos de prueba'!$K$5:$K$28,"Aprobado")/COUNTIFS('I2 Casos de prueba'!$E$5:$E$28,"Sí",'I2 Casos de prueba'!$K$5:$K$28,"<>Anulado") -> 0.35714286
B23: Casos aprobados del total vigente | C23: 90 % o más | D23: =COUNTIF('I2 Casos de prueba'!$K$5:$K$28,"Aprobado")/COUNTIF('I2 Casos de prueba'!$K$5:$K$28,"<>Anulado") -> 0.30434783
B24: Defectos críticos o altos sin cerrar | C24: 0 | D24: =COUNTIFS('I5 Defectos'!$E$5:$E$11,"Crítica",'I5 Defectos'!$L$5:$L$11,"Abierto")+COUNTIFS('I5 Defectos'!$E$5:$E$11,"Crítica",'I5 Defectos'!$L$5:$L$11,"Corregido")+COUNTIFS('I5 Defectos'!$E$5:$E$11,"Alta",'I5 Defectos'!$L$5:$L$11,"Abierto")+COUNTIFS('I5 Defectos'!$E$5:$E$11,"Alta",'I5 Defectos'!$L$5:$L$11,"Corregido") -> 2

Sheet I4 No funcionales
A1: Pruebas no funcionales
A4: Tipo | B4: Requisito | C4: Qué se prueba | D4: Herramienta | E4: Criterio de aceptación | F4: Resultado obtenido | G4: Estado | H4: Sprint
A5: Seguridad | B5: RNF Seguridad · Entreg. 17 | C5: Permisos por rol, token inválido o vencido, límites de uso y cabeceras HTTP | D5: pytest + httpx; OWASP ZAP | E5: Toda escritura sin permiso responde 401 o 403; 429 al exceder el límite; ZAP sin alertas altas | G5: Pendiente | H5: 7
A6: Rendimiento | B6: RNF Rendimiento | C6: Búsqueda y filtros del catálogo | D6: Locust | E6: El 95 % de las respuestas en 2 s o menos | G6: Pendiente | H6: 7
A7: Carga | B7: RNF Rendimiento | C7: 50 usuarios simultáneos durante 10 minutos | D7: Locust | E7: Menos de 1 % de errores y el mismo tiempo de respuesta | G7: Pendiente | H7: 7
A8: Concurrencia | B8: RF-10 · RF-14 | C8: Dos administradores guardan a la vez; la ingesta corre mientras se consulta | D8: pytest con hilos y transacciones | E8: Sin datos corruptos ni evaluaciones duplicadas | G8: Pendiente | H8: 7
A9: Latencia | B9: Entreg. 13 | C9: Tiempo desde que la ingesta carga una propiedad hasta el aviso | D9: Tiempos registrados en las alertas | E9: El 95 % de las alertas en menos de 5 minutos | G9: Pendiente | H9: 6
A10: Disponibilidad | B10: RNF Disponibilidad | C10: Ambiente de demostración | D10: Monitor de /health cada 5 minutos | E10: Al menos 95 % durante las pruebas y la demostración | G10: Pendiente | H10: 7
A11: Accesibilidad | B11: Sección E (WCAG 2.2) | C11: Contraste de texto, botones y colores del semáforo | D11: Cálculo de contraste WCAG sobre la paleta del prototipo | E11: Texto 4,5:1 o más; componentes 3:1 o más | F11: Texto 12,9:1; botones 6,1:1; zonas del semáforo 5,6 a 5,9:1 (28-09) | G11: Aprobado | H11: 3
A12: Accesibilidad | B12: Sección E (WCAG 2.2) | C12: Teclado y etiquetas de formularios en la web | D12: Lighthouse, axe y recorrido solo con teclado | E12: Sin errores de etiquetas; todo se opera con teclado y el foco se ve | G12: Pendiente | H12: 7
A13: Usabilidad | B13: RNF Usabilidad | C13: Registro y búsqueda de un usuario nuevo | D13: Prueba con 5 inversionistas y cuestionario SUS | E13: Menos de 5 minutos y SUS mayor a 68 | G13: Pendiente | H13: 7
A14: Geolocalización | B14: Entreg. 7 | C14: 20 direcciones de avisos reales | D14: Script de comparación con Nominatim | E14: Coordenadas dentro de la comuna del aviso; error menor a 50 m | G14: Pendiente | H14: 5
A15: Compatibilidad | B15: RNF Compatibilidad | C15: Recorridos principales | D15: Chrome, Firefox y Edge actuales; 360 px de ancho | E15: Mismo resultado en los tres navegadores | G15: Pendiente | H15: 7
A16: IA / modelo | B16: — | C16: No aplica: el semáforo es un motor de reglas explícitas, sin modelo de IA | D16: — | E16: — | G16: No aplica | H16: —

Sheet I5 Defectos
A1: Gestión de defectos
A4: ID | B4: Defecto | C4: Caso | D4: HU | E4: Severidad | F4: Prioridad | G4: Detectado | H4: Responsable | I4: Corrección | J4: Re-prueba | K4: Cierre | L4: Estado
A5: DEF-01 | B5: Dos propiedades de prueba quedaron sin evaluación después de guardarlas | C5: CP-12 | D5: HU-03 | E5: Alta | F5: Alta | G5: 46293 | H5: José Pizarro | I5: Calcular la evaluación dentro de la misma transacción del guardado (01-10) | J5: Pendiente (CP-12) | L5: Corregido
A6: DEF-02 | B6: Al editar una propiedad se duplican comparables y deudas | C6: CP-13 | D6: HU-03 | E6: Alta | F6: Alta | G6: 46293 | H6: José Pizarro | I6: Sangría corregida en _guardar_datos_relacionados (29-09) | J6: Pendiente (CP-13) | L6: Corregido
A7: DEF-03 | B7: Crear una propiedad no es atómica: si falla un paso quedan datos a medias | C7: CP-12 | D7: HU-03 | E7: Media | F7: Media | G7: 46293 | H7: José Pizarro | I7: Una sola transacción para la propiedad y sus tablas relacionadas (04-10) | J7: Pendiente (CP-12) | L7: Corregido
A8: DEF-04 | B8: La vista de detalle de la web no compila | C8: CP-14 | D8: HU-02 | E8: Alta | F8: Alta | G8: 46293 | H8: José Pizarro | I8: PropertyDetailPage con los campos de la API (29-09) | J8: 29-09: el proyecto compila sin errores | K8: 46294 | L8: Cerrado
A9: DEF-05 | B9: El formulario del administrador envía 0 en vez de vacío y no permite editar | C9: CP-15 | D9: HU-08 | E9: Media | F9: Baja | G9: 46293 | H9: — | I9: No aplica: el administrador ya no crea propiedades (29-09) | J9: No aplica | K9: 46294 | L9: Anulado
A10: DEF-06 | B10: El umbral de estado legal daba zona verde con 2 gravámenes | C10: CP-08 | D10: HU-03 | E10: Crítica | F10: Alta | G10: 46293 | H10: Matías Negrete | I10: Umbrales: verde con 1 acreedor, amarilla con 2 a 3 y roja con 4 o más | J10: 28-09: 2, 1, 1 y 0 puntos (CP-08) | K10: 46293 | L10: Cerrado
A11: DEF-07 | B11: El encabezado de la web queda apretado en el celular | C11: — | D11: HU-02 | E11: Baja | F11: Baja | G11: 46294 | H11: José Pizarro | I11: Ajustar el encabezado en pantallas angostas | J11: Pendiente | L11: Abierto
B13: Defectos por severidad y estado
B14: Severidad | C14: Abierto | D14: Corregido | E14: Cerrado | F14: Anulado | G14: Total
B15: Crítica | C15: =COUNTIFS($E$5:$E$11,$B15,$L$5:$L$11,C$14) -> 0 | D15: =COUNTIFS($E$5:$E$11,$B15,$L$5:$L$11,D$14) -> 0 | E15: =COUNTIFS($E$5:$E$11,$B15,$L$5:$L$11,E$14) -> 1 | F15: =COUNTIFS($E$5:$E$11,$B15,$L$5:$L$11,F$14) -> 0 | G15: =SUM(C15:F15) -> 1
B16: Alta | C16: =COUNTIFS($E$5:$E$11,$B16,$L$5:$L$11,C$14) -> 0 | D16: =COUNTIFS($E$5:$E$11,$B16,$L$5:$L$11,D$14) -> 2 | E16: =COUNTIFS($E$5:$E$11,$B16,$L$5:$L$11,E$14) -> 1 | F16: =COUNTIFS($E$5:$E$11,$B16,$L$5:$L$11,F$14) -> 0 | G16: =SUM(C16:F16) -> 3
B17: Media | C17: =COUNTIFS($E$5:$E$11,$B17,$L$5:$L$11,C$14) -> 0 | D17: =COUNTIFS($E$5:$E$11,$B17,$L$5:$L$11,D$14) -> 1 | E17: =COUNTIFS($E$5:$E$11,$B17,$L$5:$L$11,E$14) -> 0 | F17: =COUNTIFS($E$5:$E$11,$B17,$L$5:$L$11,F$14) -> 1 | G17: =SUM(C17:F17) -> 2
B18: Baja | C18: =COUNTIFS($E$5:$E$11,$B18,$L$5:$L$11,C$14) -> 1 | D18: =COUNTIFS($E$5:$E$11,$B18,$L$5:$L$11,D$14) -> 0 | E18: =COUNTIFS($E$5:$E$11,$B18,$L$5:$L$11,E$14) -> 0 | F18: =COUNTIFS($E$5:$E$11,$B18,$L$5:$L$11,F$14) -> 0 | G18: =SUM(C18:F18) -> 1
A21: Criterios de severidad
A22: Severidad | B22: Criterio
A23: Crítica | B23: El semáforo entrega una zona equivocada o el sistema se cae
A24: Alta | B24: Bloquea una historia
A25: Media | B25: Hay una forma de seguir trabajando
A26: Baja | B26: Visual o de redacción
